<?xml version="1.0" encoding="UTF-8"?>
<?xml-stylesheet type="text/xsl" charset="UTF-8" href="/xslt/nascar/race-v3.0.xsl"?>
<!-- Generation started @ 2017-04-02 22:26:20 +0000 -->
<race xmlns="http://feed.elasticstats.com/schema/nascar/race-v3.0.xsd" id="a450d0fa-4d4c-447a-a0eb-436c2c97ede6" name="STP 500" status="closed" condition="normal" number="6" distance="263" laps="500" actual_distance="263.0" purse="0.0" laps_completed="500" avg_speed="70.139" victory_margin="1.806" elapsed_time="03:44:59" lead_changes="18" cautions="14" caution_laps="95" scheduled="2017-04-02T18:00:00+00:00" start_time="2017-04-02T18:00:00+00:00" end_time="2017-04-02T22:00:00+00:00">
  <track name="Martinsville Speedway" distance="0.526" shape="Oval" banking="Turns:12;Backstretch:0;Frontstretch:0" frontstretch="800" backstretch="800" seating="65000" id="409dd8fb-2ab9-4181-9f0f-99545083b689"/>
  <comments>
    <![CDATA[]]>
  </comments>
  <flags>
    <flag sequence="1" lap="-1" flag_state="noactiverun">
    </flag>
    <flag sequence="2" lap="0" flag_state="warmup">
    </flag>
    <flag sequence="3" lap="0" flag_state="warmup">
    </flag>
    <flag sequence="4" lap="0" flag_state="green">
    </flag>
    <flag sequence="5" lap="69" flag_state="yellow">
      <comments>
        <![CDATA[#17 and 27 Incident in Turn 3]]>
      </comments>
      <beneficiary>
        <![CDATA[13]]>
      </beneficiary>
    </flag>
    <flag sequence="6" lap="75" flag_state="green">
    </flag>
    <flag sequence="7" lap="106" flag_state="yellow">
      <comments>
        <![CDATA[#1 Incident in Turn 1]]>
      </comments>
      <beneficiary>
        <![CDATA[72]]>
      </beneficiary>
    </flag>
    <flag sequence="8" lap="116" flag_state="green">
    </flag>
    <flag sequence="9" lap="122" flag_state="yellow">
      <comments>
        <![CDATA[#21 and 88 Incident in Turn 2]]>
      </comments>
      <beneficiary>
        <![CDATA[10]]>
      </beneficiary>
    </flag>
    <flag sequence="10" lap="126" flag_state="green">
    </flag>
    <flag sequence="11" lap="130" flag_state="yellow">
      <comments>
        <![CDATA[Stage 1 Conclusion]]>
      </comments>
      <beneficiary>
        <![CDATA[17]]>
      </beneficiary>
    </flag>
    <flag sequence="12" lap="140" flag_state="green">
    </flag>
    <flag sequence="13" lap="260" flag_state="yellow">
      <comments>
        <![CDATA[Stage 2 Conclusion]]>
      </comments>
      <beneficiary>
        <![CDATA[37]]>
      </beneficiary>
    </flag>
    <flag sequence="14" lap="272" flag_state="green">
    </flag>
    <flag sequence="15" lap="278" flag_state="yellow">
      <comments>
        <![CDATA[Debris in Turn 2]]>
      </comments>
      <beneficiary>
        <![CDATA[42]]>
      </beneficiary>
    </flag>
    <flag sequence="16" lap="282" flag_state="green">
    </flag>
    <flag sequence="17" lap="288" flag_state="yellow">
      <comments>
        <![CDATA[#3, 5, 19, 41, 47 and 77 incident on the frontstretch]]>
      </comments>
      <beneficiary>
        <![CDATA[10]]>
      </beneficiary>
    </flag>
    <flag sequence="18" lap="293" flag_state="green">
    </flag>
    <flag sequence="19" lap="296" flag_state="yellow">
      <comments>
        <![CDATA[#41 Incident in Turn 3]]>
      </comments>
      <beneficiary>
        <![CDATA[43]]>
      </beneficiary>
    </flag>
    <flag sequence="20" lap="301" flag_state="green">
    </flag>
    <flag sequence="21" lap="308" flag_state="yellow">
      <comments>
        <![CDATA[#23 Spin in Turn 2]]>
      </comments>
      <beneficiary>
        <![CDATA[22]]>
      </beneficiary>
    </flag>
    <flag sequence="22" lap="313" flag_state="green">
    </flag>
    <flag sequence="23" lap="333" flag_state="yellow">
      <comments>
        <![CDATA[#15 Spin in Turn 3]]>
      </comments>
      <beneficiary>
        <![CDATA[27]]>
      </beneficiary>
    </flag>
    <flag sequence="24" lap="339" flag_state="green">
    </flag>
    <flag sequence="25" lap="390" flag_state="yellow">
      <comments>
        <![CDATA[#33 Incident in Turn  2]]>
      </comments>
      <beneficiary>
        <![CDATA[5]]>
      </beneficiary>
    </flag>
    <flag sequence="26" lap="398" flag_state="green">
    </flag>
    <flag sequence="27" lap="406" flag_state="yellow">
      <comments>
        <![CDATA[#32 Incident in Turn 3]]>
      </comments>
      <beneficiary>
        <![CDATA[4]]>
      </beneficiary>
    </flag>
    <flag sequence="28" lap="413" flag_state="green">
    </flag>
    <flag sequence="29" lap="417" flag_state="yellow">
      <comments>
        <![CDATA[#5, 10, 11, 13, 43, 47 and 88 Incident in Turn 3]]>
      </comments>
      <beneficiary>
        <![CDATA[77]]>
      </beneficiary>
    </flag>
    <flag sequence="30" lap="425" flag_state="green">
    </flag>
    <flag sequence="31" lap="430" flag_state="yellow">
      <comments>
        <![CDATA[#14, 20 and 78 Incident in Turn 4]]>
      </comments>
      <beneficiary>
        <![CDATA[72]]>
      </beneficiary>
    </flag>
    <flag sequence="32" lap="435" flag_state="green">
    </flag>
    <flag sequence="33" lap="500" flag_state="finish">
    </flag>
  </flags>
  <results>
    <result start_position="4" position="1" status="running" pit_stops="6" best_lap="10" best_lap_speed="92.947" best_lap_time="20.373" elapsed_time="13524.061" fastest_laps="90" avg_position="5.148" avg_speed="70.142" passes_made="65" quality_passes="41" times_passed="34" passing_differential="31" last_lap_speed="87.505" last_lap_time="21.64" avg_restart_speed="90.168" points="55" bonus_points="15" penalty_points="0" stage_1_points="7" stage_2_points="8" money="0.0" laps_led="116" times_led="4" laps_completed="500">
      <car number="2" sponsors="Miller Lite/Alliance Truck Parts/Wurth/AutoTrader.com/SKF/Snap-on/Fitzgerald Glider Kits" crew_chief="Paul Wolfe" id="3d0cf0c8-f933-48ac-a935-71f1d18d4bd5">
        <manufacturer id="12844047-ab59-43ca-ab6c-c10d54931715" name="Ford"/>
        <owner id="3a02ed9a-855e-446a-b71b-876861b84f60" name="Roger Penske"/>
        <team id="e337709c-9fb6-4275-ad89-d9c100e71a1d" name="Team Penske">
          <owner id="57198af5-d912-4efc-9135-95fc6c0a3fc5" name="Roger Penske"/>
        </team>
      </car>
      <driver first_name="Brad" last_name="Keselowski" full_name="Brad Keselowski" points_eligible="true" id="0ce4113d-34c8-4272-b658-3b929238dbd3"/>
      <pit-stops>
        <pit-stop sequence="1" lap="0" leader_lap="0" positions_gained="0" in_time="0.0" out_time="0.0"/>
        <pit-stop sequence="2" lap="71" leader_lap="71" positions_gained="0" in_time="1562.621" out_time="1608.931"/>
        <pit-stop sequence="3" lap="134" leader_lap="134" positions_gained="-4" in_time="3631.871" out_time="3680.963"/>
        <pit-stop sequence="4" lap="265" leader_lap="265" positions_gained="-1" in_time="6820.648" out_time="6870.021"/>
        <pit-stop sequence="5" lap="335" leader_lap="335" positions_gained="0" in_time="9118.093" out_time="9165.054"/>
        <pit-stop sequence="6" lap="393" leader_lap="393" positions_gained="0" in_time="10527.867" out_time="10574.736"/>
      </pit-stops>
      <laps-led>
        <lead sequence="1" start_lap="24" end_lap="71"/>
        <lead sequence="2" start_lap="406" end_lap="415"/>
        <lead sequence="3" start_lap="429" end_lap="443"/>
        <lead sequence="4" start_lap="458" end_lap="500"/>
      </laps-led>
    </result>
    <result start_position="10" position="2" status="running" pit_stops="7" best_lap="305" best_lap_speed="93.253" best_lap_time="20.306" elapsed_time="13500.224" fastest_laps="91" avg_position="3.18" avg_speed="70.132" passes_made="40" quality_passes="40" times_passed="31" passing_differential="9" last_lap_speed="88.449" last_lap_time="21.409" avg_restart_speed="90.837" points="52" bonus_points="17" penalty_points="0" stage_1_points="8" stage_2_points="9" money="0.0" laps_led="274" times_led="7" laps_completed="500">
      <car number="18" sponsors="M&amp;M's/Skittles/Interstate Batteries/Snickers" crew_chief="Adam Stevens" id="17765fdf-5d63-4795-80ae-9149c91729c4">
        <manufacturer id="73364deb-a012-4625-b759-db6a236797e3" name="Toyota"/>
        <owner id="e7846c1b-f64e-4312-8ee3-13c8a0001a8b" name="Joe Gibbs"/>
        <team id="b30dee06-c437-4e76-8b9c-8b850d52ce21" name="Joe Gibbs Racing">
        </team>
      </car>
      <driver first_name="Kyle" last_name="Busch" full_name="Kyle Busch" points_eligible="true" id="85c06960-3610-4eff-9ef2-18641b84c952"/>
      <pit-stops>
        <pit-stop sequence="1" lap="0" leader_lap="0" positions_gained="0" in_time="0.0" out_time="0.0"/>
        <pit-stop sequence="2" lap="71" leader_lap="71" positions_gained="3" in_time="1568.777" out_time="1615.08"/>
        <pit-stop sequence="3" lap="108" leader_lap="108" positions_gained="-3" in_time="2550.446" out_time="2599.048"/>
        <pit-stop sequence="4" lap="265" leader_lap="265" positions_gained="0" in_time="6820.186" out_time="6866.689"/>
        <pit-stop sequence="5" lap="335" leader_lap="335" positions_gained="0" in_time="9117.654" out_time="9162.507"/>
        <pit-stop sequence="6" lap="393" leader_lap="393" positions_gained="0" in_time="10525.838" out_time="10570.63"/>
        <pit-stop sequence="7" lap="500" leader_lap="500" positions_gained="0" in_time="13529.504" out_time="0.0"/>
      </pit-stops>
      <laps-led>
        <lead sequence="1" start_lap="109" end_lap="109"/>
        <lead sequence="2" start_lap="136" end_lap="144"/>
        <lead sequence="3" start_lap="152" end_lap="259"/>
        <lead sequence="4" start_lap="273" end_lap="336"/>
        <lead sequence="5" start_lap="341" end_lap="405"/>
        <lead sequence="6" start_lap="416" end_lap="428"/>
        <lead sequence="7" start_lap="444" end_lap="457"/>
      </laps-led>
    </result>
    <result start_position="2" position="3" status="running" pit_stops="7" best_lap="276" best_lap_speed="92.887" best_lap_time="20.386" elapsed_time="13500.57" fastest_laps="38" avg_position="3.374" avg_speed="70.13" passes_made="42" quality_passes="40" times_passed="38" passing_differential="4" last_lap_speed="88.321" last_lap_time="21.44" avg_restart_speed="90.257" points="50" bonus_points="16" penalty_points="0" stage_1_points="6" stage_2_points="10" money="0.0" stage_2_win="true" laps_led="20" times_led="2" laps_completed="500">
      <car number="24" sponsors="NAPA Auto Parts/3M/SunEnergy1/Kelley Blue Book/Mountain Dew/Hooter's" crew_chief="Alan Gustafson" id="7cef9b08-2b70-402f-b5b5-c33c623d3126">
        <manufacturer id="dbf04b7a-c4a2-4cff-9dd0-cf1977fc446e" name="Chevrolet"/>
        <owner id="57fb4b0f-140e-47c6-8710-9e24614b4ff4" name="Rick Hendrick"/>
        <team id="8427da4c-9c88-4849-9242-0c184d5ed67c" name="Hendrick Motorsports">
          <owner id="df3acab4-1712-44bb-b913-897b4e20fd50" name="Rick Hendrick"/>
        </team>
      </car>
      <driver first_name="Chase" last_name="Elliott" full_name="Chase Elliott" points_eligible="true" id="5fd3e3fb-322f-4157-ae41-9317fba1997d"/>
      <pit-stops>
        <pit-stop sequence="1" lap="0" leader_lap="0" positions_gained="0" in_time="0.0" out_time="0.0"/>
        <pit-stop sequence="2" lap="71" leader_lap="71" positions_gained="-1" in_time="1566.495" out_time="1614.347"/>
        <pit-stop sequence="3" lap="108" leader_lap="108" positions_gained="-3" in_time="2552.9" out_time="2599.838"/>
        <pit-stop sequence="4" lap="265" leader_lap="265" positions_gained="0" in_time="6819.694" out_time="6865.794"/>
        <pit-stop sequence="5" lap="335" leader_lap="335" positions_gained="0" in_time="9118.631" out_time="9165.389"/>
        <pit-stop sequence="6" lap="393" leader_lap="393" positions_gained="0" in_time="10527.465" out_time="10573.435"/>
        <pit-stop sequence="7" lap="500" leader_lap="500" positions_gained="0" in_time="13539.293" out_time="0.0"/>
      </pit-stops>
      <laps-led>
        <lead sequence="1" start_lap="145" end_lap="151"/>
        <lead sequence="2" start_lap="260" end_lap="272"/>
      </laps-led>
    </result>
    <result start_position="5" position="4" status="running" pit_stops="9" best_lap="5" best_lap_speed="92.303" best_lap_time="20.515" elapsed_time="13502.97" fastest_laps="48" avg_position="11.198" avg_speed="70.118" passes_made="69" quality_passes="31" times_passed="63" passing_differential="6" last_lap_speed="87.927" last_lap_time="21.536" avg_restart_speed="88.918" points="33" bonus_points="0" penalty_points="0" stage_1_points="0" stage_2_points="0" money="0.0" laps_led="1" times_led="1" laps_completed="500">
      <car number="22" sponsors="Shell-Pennzoil/AAA/AutoTrader.com/Duralast" crew_chief="Todd Gordon" id="23a4be38-3039-4757-94f5-b4e478e4d7f8">
        <manufacturer id="12844047-ab59-43ca-ab6c-c10d54931715" name="Ford"/>
        <owner id="03246399-5e63-4c21-9c5f-24074e3bf515" name="Walter Czarnecki"/>
        <team id="e337709c-9fb6-4275-ad89-d9c100e71a1d" name="Team Penske">
          <owner id="57198af5-d912-4efc-9135-95fc6c0a3fc5" name="Roger Penske"/>
        </team>
      </car>
      <driver first_name="Joey" last_name="Logano" full_name="Joey Logano" points_eligible="true" id="894b273e-ce7d-446c-9ab0-d9a474ce9d7f"/>
      <pit-stops>
        <pit-stop sequence="1" lap="0" leader_lap="0" positions_gained="0" in_time="0.0" out_time="0.0"/>
        <pit-stop sequence="2" lap="71" leader_lap="71" positions_gained="0" in_time="1563.077" out_time="1610.066"/>
        <pit-stop sequence="3" lap="108" leader_lap="108" positions_gained="1" in_time="2561.007" out_time="2607.415"/>
        <pit-stop sequence="4" lap="230" leader_lap="231" positions_gained="0" in_time="5871.645" out_time="5934.998"/>
        <pit-stop sequence="5" lap="278" leader_lap="280" positions_gained="0" in_time="7377.164" out_time="7426.068"/>
        <pit-stop sequence="6" lap="311" leader_lap="312" positions_gained="0" in_time="8517.864" out_time="8576.731"/>
        <pit-stop sequence="7" lap="335" leader_lap="335" positions_gained="3" in_time="9127.029" out_time="9173.617"/>
        <pit-stop sequence="8" lap="393" leader_lap="393" positions_gained="-6" in_time="10532.613" out_time="10583.06"/>
        <pit-stop sequence="9" lap="500" leader_lap="500" positions_gained="0" in_time="13547.164" out_time="0.0"/>
      </pit-stops>
      <laps-led>
        <lead sequence="1" start_lap="72" end_lap="72"/>
      </laps-led>
    </result>
    <result start_position="20" position="5" status="running" pit_stops="10" best_lap="438" best_lap_speed="91.798" best_lap_time="20.628" elapsed_time="13503.363" fastest_laps="9" avg_position="12.0" avg_speed="70.116" passes_made="69" quality_passes="52" times_passed="64" passing_differential="5" last_lap_speed="87.931" last_lap_time="21.535" avg_restart_speed="88.997" points="34" bonus_points="2" penalty_points="0" stage_1_points="2" stage_2_points="0" money="0.0" laps_led="0" times_led="0" laps_completed="500">
      <car number="3" sponsors="Dow Chemical/American Ethanol/Bass Pro Shops/AAA/Quikrete" crew_chief="Slugger Labbe" id="fbee74ad-5e2d-4f54-bdf5-52b6193b04d6">
        <manufacturer id="dbf04b7a-c4a2-4cff-9dd0-cf1977fc446e" name="Chevrolet"/>
        <owner id="b28b1f53-bdee-4c44-97fb-bb1fd0ea4a8b" name="Richard Childress"/>
        <team id="ffd3ba10-57f2-4bb8-9aaf-7c64b1ba793a" name="Richard Childress Racing">
          <owner id="84e3b257-75b1-40ef-8774-cfb53fab90e9" name="Richard Childress"/>
        </team>
      </car>
      <driver first_name="Austin" last_name="Dillon" full_name="Austin Dillon" points_eligible="true" id="8853e676-384e-4d08-8808-970fd111f36a"/>
      <pit-stops>
        <pit-stop sequence="1" lap="0" leader_lap="0" positions_gained="0" in_time="0.0" out_time="0.0"/>
        <pit-stop sequence="2" lap="71" leader_lap="71" positions_gained="3" in_time="1571.847" out_time="1617.813"/>
        <pit-stop sequence="3" lap="108" leader_lap="108" positions_gained="7" in_time="2557.871" out_time="2598.467"/>
        <pit-stop sequence="4" lap="134" leader_lap="134" positions_gained="5" in_time="3634.036" out_time="3674.592"/>
        <pit-stop sequence="5" lap="265" leader_lap="265" positions_gained="1" in_time="6833.755" out_time="6880.752"/>
        <pit-stop sequence="6" lap="290" leader_lap="290" positions_gained="4" in_time="7747.213" out_time="7797.748"/>
        <pit-stop sequence="7" lap="310" leader_lap="310" positions_gained="-1" in_time="8456.238" out_time="8504.347"/>
        <pit-stop sequence="8" lap="335" leader_lap="335" positions_gained="0" in_time="9123.551" out_time="9169.807"/>
        <pit-stop sequence="9" lap="393" leader_lap="393" positions_gained="2" in_time="10533.038" out_time="10579.415"/>
        <pit-stop sequence="10" lap="500" leader_lap="500" positions_gained="0" in_time="13552.18" out_time="0.0"/>
      </pit-stops>
    </result>
    <result start_position="30" position="6" status="running" pit_stops="11" best_lap="8" best_lap_speed="91.789" best_lap_time="20.63" elapsed_time="13504.3" fastest_laps="10" avg_position="15.192" avg_speed="70.111" passes_made="97" quality_passes="40" times_passed="61" passing_differential="36" last_lap_speed="88.61" last_lap_time="21.37" avg_restart_speed="88.485" points="31" bonus_points="0" penalty_points="0" stage_1_points="0" stage_2_points="0" money="0.0" laps_led="0" times_led="0" laps_completed="500">
      <car number="47" sponsors="Kroger/Scott Products/Bush's Beans" crew_chief="Randall Burnett" id="efd240d0-8844-4fcb-a15f-062846ae6e4c">
        <manufacturer id="dbf04b7a-c4a2-4cff-9dd0-cf1977fc446e" name="Chevrolet"/>
        <owner id="db238547-f8d4-4999-9614-0e808d83d766" name="Tad Geschickter"/>
        <team id="fb3e4d03-9408-43c6-b65f-61a2399a146d" name="JTG Daugherty Racing">
        </team>
      </car>
      <driver first_name="AJ" last_name="Allmendinger" full_name="AJ Allmendinger" points_eligible="true" id="fc04af5e-bd27-4e87-850c-a72e22dcb4a6"/>
      <pit-stops>
        <pit-stop sequence="1" lap="0" leader_lap="0" positions_gained="0" in_time="0.0" out_time="0.0"/>
        <pit-stop sequence="2" lap="71" leader_lap="71" positions_gained="0" in_time="1576.385" out_time="1628.123"/>
        <pit-stop sequence="3" lap="108" leader_lap="108" positions_gained="-3" in_time="2559.268" out_time="2608.381"/>
        <pit-stop sequence="4" lap="134" leader_lap="134" positions_gained="1" in_time="3638.839" out_time="3691.903"/>
        <pit-stop sequence="5" lap="265" leader_lap="265" positions_gained="0" in_time="6831.322" out_time="6879.541"/>
        <pit-stop sequence="6" lap="335" leader_lap="335" positions_gained="-1" in_time="9119.583" out_time="9166.594"/>
        <pit-stop sequence="7" lap="393" leader_lap="393" positions_gained="-2" in_time="10532.122" out_time="10580.295"/>
        <pit-stop sequence="8" lap="407" leader_lap="407" positions_gained="0" in_time="11022.672" out_time="11072.66"/>
        <pit-stop sequence="9" lap="420" leader_lap="421" positions_gained="2" in_time="11555.974" out_time="11615.874"/>
        <pit-stop sequence="10" lap="422" leader_lap="423" positions_gained="0" in_time="11658.315" out_time="11712.984"/>
        <pit-stop sequence="11" lap="500" leader_lap="500" positions_gained="0" in_time="13549.636" out_time="0.0"/>
      </pit-stops>
    </result>
    <result start_position="8" position="7" status="running" pit_stops="10" best_lap="5" best_lap_speed="92.267" best_lap_time="20.523" elapsed_time="13508.039" fastest_laps="1" avg_position="12.25" avg_speed="70.092" passes_made="67" quality_passes="52" times_passed="51" passing_differential="16" last_lap_speed="85.874" last_lap_time="22.051" avg_restart_speed="88.922" points="31" bonus_points="1" penalty_points="0" stage_1_points="1" stage_2_points="0" money="0.0" laps_led="0" times_led="0" laps_completed="500">
      <car number="14" sponsors="Mobil 1/Rush Truck Centers" crew_chief="Mike Bugarewicz" id="833f8004-3392-49e4-8ef9-44158a7dc92c">
        <manufacturer id="12844047-ab59-43ca-ab6c-c10d54931715" name="Ford"/>
        <owner id="975fb88e-0122-4923-8720-24e60dfb65b3" name="Margaret Haas"/>
        <team id="876a07ff-ff53-4f23-9528-6d9795270244" name="Stewart Haas Racing">
          <owner id="160c7b9e-b198-4b4d-9000-bcdc1a094cee" name="Tony Stewart"/>
        </team>
      </car>
      <driver first_name="Clint" last_name="Bowyer" full_name="Clint Bowyer" points_eligible="true" id="bcf5b54b-bbbe-4653-aade-a7364e946056"/>
      <pit-stops>
        <pit-stop sequence="1" lap="0" leader_lap="0" positions_gained="0" in_time="0.0" out_time="0.0"/>
        <pit-stop sequence="2" lap="71" leader_lap="71" positions_gained="0" in_time="1569.332" out_time="1617.0"/>
        <pit-stop sequence="3" lap="108" leader_lap="108" positions_gained="-5" in_time="2555.654" out_time="2603.901"/>
        <pit-stop sequence="4" lap="134" leader_lap="134" positions_gained="-6" in_time="3634.632" out_time="3706.976"/>
        <pit-stop sequence="5" lap="265" leader_lap="265" positions_gained="1" in_time="6833.333" out_time="6879.666"/>
        <pit-stop sequence="6" lap="290" leader_lap="290" positions_gained="-1" in_time="7738.555" out_time="7807.227"/>
        <pit-stop sequence="7" lap="310" leader_lap="310" positions_gained="1" in_time="8457.132" out_time="8503.639"/>
        <pit-stop sequence="8" lap="335" leader_lap="335" positions_gained="1" in_time="9123.071" out_time="9168.82"/>
        <pit-stop sequence="9" lap="393" leader_lap="393" positions_gained="3" in_time="10533.865" out_time="10579.989"/>
        <pit-stop sequence="10" lap="500" leader_lap="500" positions_gained="0" in_time="13573.682" out_time="0.0"/>
      </pit-stops>
    </result>
    <result start_position="11" position="8" status="running" pit_stops="12" best_lap="4" best_lap_speed="92.461" best_lap_time="20.48" elapsed_time="13509.562" fastest_laps="1" avg_position="12.944" avg_speed="70.084" passes_made="40" quality_passes="34" times_passed="53" passing_differential="-13" last_lap_speed="87.939" last_lap_time="21.533" avg_restart_speed="88.574" points="29" bonus_points="0" penalty_points="0" stage_1_points="0" stage_2_points="0" money="0.0" laps_led="0" times_led="0" laps_completed="500">
      <car number="31" sponsors="Caterpillar/Grainger" crew_chief="Luke Lambert" id="c2351769-a323-4eba-8553-ff34d122ffae">
        <manufacturer id="dbf04b7a-c4a2-4cff-9dd0-cf1977fc446e" name="Chevrolet"/>
        <owner id="b28b1f53-bdee-4c44-97fb-bb1fd0ea4a8b" name="Richard Childress"/>
        <team id="ffd3ba10-57f2-4bb8-9aaf-7c64b1ba793a" name="Richard Childress Racing">
          <owner id="84e3b257-75b1-40ef-8774-cfb53fab90e9" name="Richard Childress"/>
        </team>
      </car>
      <driver first_name="Ryan" last_name="Newman" full_name="Ryan Newman" points_eligible="true" id="2e6f5ea3-ea6e-48d2-85ec-2e89c2fa02b4"/>
      <pit-stops>
        <pit-stop sequence="1" lap="0" leader_lap="0" positions_gained="0" in_time="0.0" out_time="0.0"/>
        <pit-stop sequence="2" lap="71" leader_lap="71" positions_gained="-1" in_time="1572.327" out_time="1620.319"/>
        <pit-stop sequence="3" lap="108" leader_lap="108" positions_gained="2" in_time="2559.793" out_time="2606.592"/>
        <pit-stop sequence="4" lap="124" leader_lap="124" positions_gained="0" in_time="3184.797" out_time="3233.268"/>
        <pit-stop sequence="5" lap="262" leader_lap="263" positions_gained="0" in_time="6649.322" out_time="6716.325"/>
        <pit-stop sequence="6" lap="265" leader_lap="265" positions_gained="0" in_time="6835.21" out_time="6891.255"/>
        <pit-stop sequence="7" lap="279" leader_lap="280" positions_gained="0" in_time="7377.747" out_time="7426.79"/>
        <pit-stop sequence="8" lap="310" leader_lap="310" positions_gained="0" in_time="8455.196" out_time="8502.674"/>
        <pit-stop sequence="9" lap="335" leader_lap="335" positions_gained="0" in_time="9124.078" out_time="9172.041"/>
        <pit-stop sequence="10" lap="393" leader_lap="393" positions_gained="1" in_time="10534.74" out_time="10581.127"/>
        <pit-stop sequence="11" lap="394" leader_lap="394" positions_gained="0" in_time="10581.127" out_time="0.0"/>
        <pit-stop sequence="12" lap="500" leader_lap="500" positions_gained="0" in_time="13568.438" out_time="0.0"/>
      </pit-stops>
    </result>
    <result start_position="25" position="9" status="running" pit_stops="9" best_lap="277" best_lap_speed="92.38" best_lap_time="20.498" elapsed_time="13509.705" fastest_laps="5" avg_position="10.498" avg_speed="70.083" passes_made="59" quality_passes="41" times_passed="39" passing_differential="20" last_lap_speed="87.675" last_lap_time="21.598" avg_restart_speed="89.409" points="32" bonus_points="4" penalty_points="0" stage_1_points="0" stage_2_points="4" money="0.0" laps_led="0" times_led="0" laps_completed="500">
      <car number="20" sponsors="DeWalt/Tide/Interstate Batteries" crew_chief="Jason Ratcliff" id="278372b1-c038-4238-8a42-f53604ab6b02">
        <manufacturer id="73364deb-a012-4625-b759-db6a236797e3" name="Toyota"/>
        <owner id="e7846c1b-f64e-4312-8ee3-13c8a0001a8b" name="Joe Gibbs"/>
        <team id="b30dee06-c437-4e76-8b9c-8b850d52ce21" name="Joe Gibbs Racing">
        </team>
      </car>
      <driver first_name="Matt" last_name="Kenseth" full_name="Matt Kenseth" points_eligible="true" id="04687e5d-3ff9-479a-ae3e-6a4cee7b4d09"/>
      <pit-stops>
        <pit-stop sequence="1" lap="0" leader_lap="0" positions_gained="0" in_time="0.0" out_time="0.0"/>
        <pit-stop sequence="2" lap="71" leader_lap="71" positions_gained="2" in_time="1573.374" out_time="1619.861"/>
        <pit-stop sequence="3" lap="108" leader_lap="108" positions_gained="-5" in_time="2557.067" out_time="2607.189"/>
        <pit-stop sequence="4" lap="124" leader_lap="124" positions_gained="0" in_time="3185.854" out_time="3234.281"/>
        <pit-stop sequence="5" lap="265" leader_lap="265" positions_gained="1" in_time="6828.573" out_time="6875.084"/>
        <pit-stop sequence="6" lap="335" leader_lap="335" positions_gained="1" in_time="9120.06" out_time="9166.388"/>
        <pit-stop sequence="7" lap="393" leader_lap="393" positions_gained="0" in_time="10531.258" out_time="10577.014"/>
        <pit-stop sequence="8" lap="432" leader_lap="432" positions_gained="0" in_time="11980.238" out_time="12026.749"/>
        <pit-stop sequence="9" lap="500" leader_lap="500" positions_gained="0" in_time="13567.518" out_time="0.0"/>
      </pit-stops>
    </result>
    <result start_position="24" position="10" status="running" pit_stops="13" best_lap="7" best_lap_speed="91.214" best_lap_time="20.76" elapsed_time="13511.834" fastest_laps="13" avg_position="19.59" avg_speed="70.072" passes_made="64" quality_passes="19" times_passed="69" passing_differential="-5" last_lap_speed="87.541" last_lap_time="21.631" avg_restart_speed="88.211" points="27" bonus_points="0" penalty_points="0" stage_1_points="0" stage_2_points="0" money="0.0" laps_led="0" times_led="0" laps_completed="500">
      <car number="17" sponsors="Fastenal/Fifth Third Bank/Sunny D" crew_chief="Brian Pattie" id="a7fc0b6d-da2f-4cb6-9f7d-154e5351d788">
        <manufacturer id="12844047-ab59-43ca-ab6c-c10d54931715" name="Ford"/>
        <owner id="4788307e-e269-4409-8fae-bbda98214196" name="Jack Roush"/>
        <team id="69cd5f7e-cb9d-46c0-a2c3-c1dde01969ee" name="Roush Fenway Racing">
        </team>
      </car>
      <driver first_name="Ricky" last_name="Stenhouse" full_name="Ricky Stenhouse Jr" points_eligible="true" id="0cdae85e-0b1d-44d7-9614-a49aff66aeb5"/>
      <pit-stops>
        <pit-stop sequence="1" lap="0" leader_lap="0" positions_gained="0" in_time="0.0" out_time="0.0"/>
        <pit-stop sequence="2" lap="70" leader_lap="71" positions_gained="0" in_time="1575.888" out_time="1636.603"/>
        <pit-stop sequence="3" lap="135" leader_lap="135" positions_gained="0" in_time="3695.686" out_time="3754.327"/>
        <pit-stop sequence="4" lap="265" leader_lap="265" positions_gained="0" in_time="6834.246" out_time="6883.726"/>
        <pit-stop sequence="5" lap="266" leader_lap="266" positions_gained="0" in_time="6883.726" out_time="0.0"/>
        <pit-stop sequence="6" lap="290" leader_lap="290" positions_gained="-2" in_time="7739.624" out_time="7813.532"/>
        <pit-stop sequence="7" lap="297" leader_lap="297" positions_gained="1" in_time="8024.98" out_time="8086.407"/>
        <pit-stop sequence="8" lap="310" leader_lap="310" positions_gained="2" in_time="8460.106" out_time="8508.139"/>
        <pit-stop sequence="9" lap="393" leader_lap="393" positions_gained="0" in_time="10536.212" out_time="10584.2"/>
        <pit-stop sequence="10" lap="407" leader_lap="407" positions_gained="-1" in_time="11024.845" out_time="11095.767"/>
        <pit-stop sequence="11" lap="409" leader_lap="410" positions_gained="0" in_time="11135.485" out_time="11196.18"/>
        <pit-stop sequence="12" lap="411" leader_lap="412" positions_gained="0" in_time="11244.835" out_time="11293.145"/>
        <pit-stop sequence="13" lap="500" leader_lap="500" positions_gained="0" in_time="13592.914" out_time="0.0"/>
      </pit-stops>
    </result>
    <result start_position="33" position="11" status="running" pit_stops="10" best_lap="442" best_lap_speed="91.135" best_lap_time="20.778" elapsed_time="13513.171" fastest_laps="0" avg_position="18.356" avg_speed="70.065" passes_made="46" quality_passes="13" times_passed="56" passing_differential="-10" last_lap_speed="87.557" last_lap_time="21.627" avg_restart_speed="88.186" points="26" bonus_points="0" penalty_points="0" stage_1_points="0" stage_2_points="0" money="0.0" laps_led="0" times_led="0" laps_completed="500">
      <car number="37" sponsors="Cottonelle/Bush's Baked Beans/Scott Products/Kingsford/Kroger/Natural Light" crew_chief="Trent Owens" id="6a4b77bf-0f1a-45a3-ba5c-2b1e8c51a354">
        <manufacturer id="dbf04b7a-c4a2-4cff-9dd0-cf1977fc446e" name="Chevrolet"/>
        <owner id="db238547-f8d4-4999-9614-0e808d83d766" name="Tad Geschickter"/>
        <team id="fb3e4d03-9408-43c6-b65f-61a2399a146d" name="JTG Daugherty Racing">
        </team>
      </car>
      <driver first_name="Chris" last_name="Buescher" full_name="Chris Buescher" points_eligible="true" id="25cfebb6-24e5-429c-a9db-c276bab0e228"/>
      <pit-stops>
        <pit-stop sequence="1" lap="0" leader_lap="0" positions_gained="0" in_time="0.0" out_time="0.0"/>
        <pit-stop sequence="2" lap="108" leader_lap="109" positions_gained="0" in_time="2568.085" out_time="2621.342"/>
        <pit-stop sequence="3" lap="124" leader_lap="124" positions_gained="0" in_time="3189.63" out_time="3239.141"/>
        <pit-stop sequence="4" lap="266" leader_lap="266" positions_gained="0" in_time="6881.982" out_time="6933.303"/>
        <pit-stop sequence="5" lap="279" leader_lap="279" positions_gained="0" in_time="7376.072" out_time="7422.175"/>
        <pit-stop sequence="6" lap="290" leader_lap="290" positions_gained="-3" in_time="7737.954" out_time="7809.02"/>
        <pit-stop sequence="7" lap="310" leader_lap="310" positions_gained="-2" in_time="8458.887" out_time="8525.944"/>
        <pit-stop sequence="8" lap="335" leader_lap="335" positions_gained="0" in_time="9126.524" out_time="9176.617"/>
        <pit-stop sequence="9" lap="393" leader_lap="393" positions_gained="1" in_time="10537.208" out_time="10585.037"/>
        <pit-stop sequence="10" lap="500" leader_lap="500" positions_gained="0" in_time="13578.359" out_time="0.0"/>
      </pit-stops>
    </result>
    <result start_position="15" position="12" status="running" pit_stops="12" best_lap="9" best_lap_speed="91.686" best_lap_time="20.653" elapsed_time="13513.404" fastest_laps="7" avg_position="14.944" avg_speed="70.064" passes_made="54" quality_passes="24" times_passed="73" passing_differential="-19" last_lap_speed="87.464" last_lap_time="21.65" avg_restart_speed="88.67" points="28" bonus_points="3" penalty_points="0" stage_1_points="0" stage_2_points="3" money="0.0" laps_led="0" times_led="0" laps_completed="500">
      <car number="77" sponsors="5-Hour Energy/Sport Clips/Toyota Service Centers" crew_chief="Chris Gayle" id="5d9986fb-1155-4456-a38c-d56b4a618c34">
        <manufacturer id="73364deb-a012-4625-b759-db6a236797e3" name="Toyota"/>
        <owner id="58a2e724-ba23-47ae-b1a3-3314ce83f3bc" name="Barney Visser"/>
        <team id="7e4712e1-9276-4f32-b648-79fc4fa42e7f" name="Furniture Row Motorsports">
        </team>
      </car>
      <driver first_name="Erik" last_name="Jones" full_name="Erik Jones" points_eligible="true" id="e595780e-baa7-4988-9a19-311fef7414d5"/>
      <pit-stops>
        <pit-stop sequence="1" lap="0" leader_lap="0" positions_gained="0" in_time="0.0" out_time="0.0"/>
        <pit-stop sequence="2" lap="71" leader_lap="71" positions_gained="1" in_time="1574.711" out_time="1622.126"/>
        <pit-stop sequence="3" lap="108" leader_lap="108" positions_gained="0" in_time="2562.676" out_time="2611.717"/>
        <pit-stop sequence="4" lap="265" leader_lap="265" positions_gained="-1" in_time="6829.35" out_time="6876.664"/>
        <pit-stop sequence="5" lap="290" leader_lap="290" positions_gained="0" in_time="7736.825" out_time="7784.277"/>
        <pit-stop sequence="6" lap="335" leader_lap="335" positions_gained="-4" in_time="9125.017" out_time="9183.362"/>
        <pit-stop sequence="7" lap="381" leader_lap="382" positions_gained="0" in_time="10230.941" out_time="10280.868"/>
        <pit-stop sequence="8" lap="407" leader_lap="408" positions_gained="0" in_time="11077.885" out_time="11127.942"/>
        <pit-stop sequence="9" lap="422" leader_lap="423" positions_gained="0" in_time="11657.54" out_time="11719.97"/>
        <pit-stop sequence="10" lap="424" leader_lap="424" positions_gained="0" in_time="11753.311" out_time="11795.698"/>
        <pit-stop sequence="11" lap="432" leader_lap="432" positions_gained="1" in_time="11991.018" out_time="12044.592"/>
        <pit-stop sequence="12" lap="500" leader_lap="500" positions_gained="0" in_time="13590.559" out_time="0.0"/>
      </pit-stops>
    </result>
    <result start_position="16" position="13" status="running" pit_stops="9" best_lap="5" best_lap_speed="92.092" best_lap_time="20.562" elapsed_time="13514.435" fastest_laps="1" avg_position="13.71" avg_speed="70.058" passes_made="48" quality_passes="35" times_passed="53" passing_differential="-5" last_lap_speed="87.707" last_lap_time="21.59" avg_restart_speed="88.685" points="26" bonus_points="2" penalty_points="0" stage_1_points="0" stage_2_points="2" money="0.0" laps_led="0" times_led="0" laps_completed="500">
      <car number="6" sponsors="AdvoCare/Liberty National Life Insurance Company/Performance Plus Oil" crew_chief="Matt Puccia" id="698eee4f-6812-47b1-9940-62e2afc50143">
        <manufacturer id="12844047-ab59-43ca-ab6c-c10d54931715" name="Ford"/>
        <owner id="b8e569e0-a3cf-48ee-bd7b-52a2ba1ff1d9" name="John Henry"/>
        <team id="69cd5f7e-cb9d-46c0-a2c3-c1dde01969ee" name="Roush Fenway Racing">
        </team>
      </car>
      <driver first_name="Trevor" last_name="Bayne" full_name="Trevor Bayne" points_eligible="true" id="dde7052f-25f0-4e9e-9779-6bc2943bac99"/>
      <pit-stops>
        <pit-stop sequence="1" lap="0" leader_lap="0" positions_gained="0" in_time="0.0" out_time="0.0"/>
        <pit-stop sequence="2" lap="71" leader_lap="71" positions_gained="-1" in_time="1573.831" out_time="1623.009"/>
        <pit-stop sequence="3" lap="108" leader_lap="108" positions_gained="0" in_time="2564.37" out_time="2612.921"/>
        <pit-stop sequence="4" lap="265" leader_lap="265" positions_gained="2" in_time="6829.8" out_time="6876.59"/>
        <pit-stop sequence="5" lap="310" leader_lap="310" positions_gained="0" in_time="8454.226" out_time="8501.298"/>
        <pit-stop sequence="6" lap="335" leader_lap="335" positions_gained="1" in_time="9122.401" out_time="9168.675"/>
        <pit-stop sequence="7" lap="393" leader_lap="393" positions_gained="2" in_time="10536.658" out_time="10583.251"/>
        <pit-stop sequence="8" lap="420" leader_lap="420" positions_gained="0" in_time="11545.155" out_time="11592.811"/>
        <pit-stop sequence="9" lap="500" leader_lap="500" positions_gained="0" in_time="13605.204" out_time="0.0"/>
      </pit-stops>
    </result>
    <result start_position="13" position="14" status="running" pit_stops="10" best_lap="8" best_lap_speed="92.24" best_lap_time="20.529" elapsed_time="13514.637" fastest_laps="2" avg_position="13.1" avg_speed="70.057" passes_made="42" quality_passes="38" times_passed="51" passing_differential="-9" last_lap_speed="87.565" last_lap_time="21.625" avg_restart_speed="88.779" points="24" bonus_points="1" penalty_points="0" stage_1_points="0" stage_2_points="1" money="0.0" laps_led="0" times_led="0" laps_completed="500">
      <car number="5" sponsors="Farmers Insurance/Great Clips/LiftMaster/Quicken Loans/Panasonic Toughbook/Mountain Dew/AARP Drive to End Hunger/UniFirst" crew_chief="Keith Rodden" id="3c900bcd-335e-40b5-a8c6-6a774f7b0347">
        <manufacturer id="dbf04b7a-c4a2-4cff-9dd0-cf1977fc446e" name="Chevrolet"/>
        <owner id="cda14f61-7d18-4863-a413-da170827ff2b" name="Linda Hendrick"/>
        <team id="8427da4c-9c88-4849-9242-0c184d5ed67c" name="Hendrick Motorsports">
          <owner id="df3acab4-1712-44bb-b913-897b4e20fd50" name="Rick Hendrick"/>
        </team>
      </car>
      <driver first_name="Kasey" last_name="Kahne" full_name="Kasey Kahne" points_eligible="true" id="18d82f63-a0b8-4354-8083-b3e47f050ff1"/>
      <pit-stops>
        <pit-stop sequence="1" lap="0" leader_lap="0" positions_gained="0" in_time="0.0" out_time="0.0"/>
        <pit-stop sequence="2" lap="71" leader_lap="71" positions_gained="2" in_time="1569.889" out_time="1616.223"/>
        <pit-stop sequence="3" lap="108" leader_lap="108" positions_gained="-2" in_time="2556.464" out_time="2603.386"/>
        <pit-stop sequence="4" lap="124" leader_lap="124" positions_gained="0" in_time="3184.19" out_time="3230.772"/>
        <pit-stop sequence="5" lap="265" leader_lap="265" positions_gained="2" in_time="6830.339" out_time="6876.601"/>
        <pit-stop sequence="6" lap="335" leader_lap="335" positions_gained="0" in_time="9121.309" out_time="9168.183"/>
        <pit-stop sequence="7" lap="336" leader_lap="336" positions_gained="0" in_time="9168.183" out_time="0.0"/>
        <pit-stop sequence="8" lap="394" leader_lap="394" positions_gained="0" in_time="10585.856" out_time="10651.563"/>
        <pit-stop sequence="9" lap="420" leader_lap="420" positions_gained="2" in_time="11545.62" out_time="11591.826"/>
        <pit-stop sequence="10" lap="500" leader_lap="500" positions_gained="0" in_time="13597.15" out_time="0.0"/>
      </pit-stops>
    </result>
    <result start_position="17" position="15" status="running" pit_stops="8" best_lap="8" best_lap_speed="92.755" best_lap_time="20.415" elapsed_time="13515.317" fastest_laps="20" avg_position="8.48" avg_speed="70.054" passes_made="72" quality_passes="56" times_passed="55" passing_differential="17" last_lap_speed="87.764" last_lap_time="21.576" avg_restart_speed="89.339" points="32" bonus_points="10" penalty_points="0" stage_1_points="3" stage_2_points="7" money="0.0" laps_led="0" times_led="0" laps_completed="500">
      <car number="48" sponsors="Lowe's Home Improvement/Kobalt Tools" crew_chief="Chad Knaus" id="733d54fb-e4f5-4829-bc2a-94af6c9c6504">
        <manufacturer id="dbf04b7a-c4a2-4cff-9dd0-cf1977fc446e" name="Chevrolet"/>
        <owner id="492ef62b-a861-4672-9940-0ec3133e04f1" name="Jeff Gordon"/>
        <team id="8427da4c-9c88-4849-9242-0c184d5ed67c" name="Hendrick Motorsports">
          <owner id="df3acab4-1712-44bb-b913-897b4e20fd50" name="Rick Hendrick"/>
        </team>
      </car>
      <driver first_name="Jimmie" last_name="Johnson" full_name="Jimmie Johnson" points_eligible="true" id="057da6c6-ad81-4c65-b6b1-64b6da9e2ee7"/>
      <pit-stops>
        <pit-stop sequence="1" lap="0" leader_lap="0" positions_gained="0" in_time="0.0" out_time="0.0"/>
        <pit-stop sequence="2" lap="71" leader_lap="71" positions_gained="1" in_time="1568.346" out_time="1615.69"/>
        <pit-stop sequence="3" lap="134" leader_lap="134" positions_gained="-1" in_time="3633.476" out_time="3680.165"/>
        <pit-stop sequence="4" lap="265" leader_lap="265" positions_gained="1" in_time="6821.803" out_time="6867.81"/>
        <pit-stop sequence="5" lap="335" leader_lap="335" positions_gained="0" in_time="9119.078" out_time="9165.8"/>
        <pit-stop sequence="6" lap="393" leader_lap="393" positions_gained="0" in_time="10531.689" out_time="10578.887"/>
        <pit-stop sequence="7" lap="420" leader_lap="420" positions_gained="-3" in_time="11540.568" out_time="11595.424"/>
        <pit-stop sequence="8" lap="500" leader_lap="500" positions_gained="0" in_time="13620.195" out_time="0.0"/>
      </pit-stops>
    </result>
    <result start_position="3" position="16" status="running" pit_stops="8" best_lap="8" best_lap_speed="92.524" best_lap_time="20.466" elapsed_time="13516.423" fastest_laps="13" avg_position="8.832" avg_speed="70.048" passes_made="38" quality_passes="34" times_passed="30" passing_differential="8" last_lap_speed="87.497" last_lap_time="21.642" avg_restart_speed="89.861" points="31" bonus_points="10" penalty_points="0" stage_1_points="10" stage_2_points="0" money="0.0" stage_1_win="true" laps_led="42" times_led="2" laps_completed="500">
      <car number="78" sponsors="Furniture Row/Denver Mattress/Bass Pro Shops/Auto-Owners Insurance/5-Hour Energy/WIX Filters" crew_chief="Cole Pearn" id="28df646d-1617-44a2-bed2-b138260d3240">
        <manufacturer id="73364deb-a012-4625-b759-db6a236797e3" name="Toyota"/>
        <owner id="58a2e724-ba23-47ae-b1a3-3314ce83f3bc" name="Barney Visser"/>
        <team id="7e4712e1-9276-4f32-b648-79fc4fa42e7f" name="Furniture Row Motorsports">
        </team>
      </car>
      <driver first_name="Martin" last_name="Truex" full_name="Martin Truex Jr" points_eligible="true" id="4d95ef3a-46cc-43c2-b340-c92cea2ed7f8"/>
      <pit-stops>
        <pit-stop sequence="1" lap="0" leader_lap="0" positions_gained="0" in_time="0.0" out_time="0.0"/>
        <pit-stop sequence="2" lap="71" leader_lap="71" positions_gained="0" in_time="1563.539" out_time="1611.439"/>
        <pit-stop sequence="3" lap="134" leader_lap="134" positions_gained="-1" in_time="3630.657" out_time="3676.565"/>
        <pit-stop sequence="4" lap="265" leader_lap="265" positions_gained="1" in_time="6830.729" out_time="6877.431"/>
        <pit-stop sequence="5" lap="335" leader_lap="335" positions_gained="-5" in_time="9120.441" out_time="9169.207"/>
        <pit-stop sequence="6" lap="393" leader_lap="393" positions_gained="1" in_time="10535.205" out_time="10581.189"/>
        <pit-stop sequence="7" lap="432" leader_lap="432" positions_gained="3" in_time="11992.599" out_time="12040.895"/>
        <pit-stop sequence="8" lap="500" leader_lap="500" positions_gained="0" in_time="13584.982" out_time="0.0"/>
      </pit-stops>
      <laps-led>
        <lead sequence="1" start_lap="73" end_lap="88"/>
        <lead sequence="2" start_lap="110" end_lap="135"/>
      </laps-led>
    </result>
    <result start_position="1" position="17" status="running" pit_stops="10" best_lap="5" best_lap_speed="93.664" best_lap_time="20.217" elapsed_time="13516.546" fastest_laps="7" avg_position="11.325" avg_speed="70.047" passes_made="64" quality_passes="53" times_passed="88" passing_differential="-24" last_lap_speed="86.874" last_lap_time="21.797" avg_restart_speed="89.28" points="25" bonus_points="5" penalty_points="0" stage_1_points="5" stage_2_points="0" money="0.0" laps_led="23" times_led="1" laps_completed="500">
      <car number="42" sponsors="Target/CreditOne Bank" crew_chief="Chad Johnston" id="1dbd3173-2412-48e7-bf44-cca9a72fc127">
        <manufacturer id="dbf04b7a-c4a2-4cff-9dd0-cf1977fc446e" name="Chevrolet"/>
        <owner id="beaaedde-491d-4a5e-a449-36f7d6383588" name="Chip Ganassi"/>
        <team id="e9897fd1-8187-4930-814d-5d05cd43d198" name="Chip Ganassi Racing">
        </team>
      </car>
      <driver first_name="Kyle" last_name="Larson" full_name="Kyle Larson" points_eligible="true" id="a756eefd-801d-4214-ab1b-0b595c21c37d"/>
      <pit-stops>
        <pit-stop sequence="1" lap="0" leader_lap="0" positions_gained="0" in_time="0.0" out_time="0.0"/>
        <pit-stop sequence="2" lap="71" leader_lap="71" positions_gained="1" in_time="1570.338" out_time="1617.802"/>
        <pit-stop sequence="3" lap="108" leader_lap="108" positions_gained="8" in_time="2557.452" out_time="2597.602"/>
        <pit-stop sequence="4" lap="134" leader_lap="134" positions_gained="0" in_time="3632.391" out_time="3677.786"/>
        <pit-stop sequence="5" lap="265" leader_lap="266" positions_gained="2" in_time="6875.207" out_time="6922.439"/>
        <pit-stop sequence="6" lap="278" leader_lap="279" positions_gained="0" in_time="7368.524" out_time="7415.327"/>
        <pit-stop sequence="7" lap="335" leader_lap="335" positions_gained="3" in_time="9121.77" out_time="9167.523"/>
        <pit-stop sequence="8" lap="393" leader_lap="393" positions_gained="1" in_time="10534.166" out_time="10580.573"/>
        <pit-stop sequence="9" lap="420" leader_lap="420" positions_gained="1" in_time="11541.08" out_time="11587.11"/>
        <pit-stop sequence="10" lap="500" leader_lap="500" positions_gained="0" in_time="13574.314" out_time="0.0"/>
      </pit-stops>
      <laps-led>
        <lead sequence="1" start_lap="1" end_lap="23"/>
      </laps-led>
    </result>
    <result start_position="18" position="18" status="running" pit_stops="13" best_lap="9" best_lap_speed="92.353" best_lap_time="20.504" elapsed_time="13516.715" fastest_laps="1" avg_position="19.014" avg_speed="70.047" passes_made="55" quality_passes="12" times_passed="67" passing_differential="-12" last_lap_speed="87.295" last_lap_time="21.692" avg_restart_speed="88.272" points="19" bonus_points="0" penalty_points="0" stage_1_points="0" stage_2_points="0" money="0.0" laps_led="0" times_led="0" laps_completed="500">
      <car number="43" sponsors="Smithfield Foods/U.S. Air Force/STP/Fresh From Florida/Waffle House" crew_chief="Drew Blickensderfer" id="e6fd7d08-83bc-4f2a-8c0b-e5c3cac57ab7">
        <manufacturer id="12844047-ab59-43ca-ab6c-c10d54931715" name="Ford"/>
        <owner id="1d488f0e-334f-464e-a3db-ae3c8bc028e9" name="Richard Petty"/>
        <team id="ee6a924b-58f4-40ea-8514-610936e32e78" name="Richard Petty Motorsports">
          <owner id="23972c17-6476-4824-aeb2-43896e2082d9" name="Richard Petty"/>
        </team>
      </car>
      <driver first_name="Aric" last_name="Almirola" full_name="Aric Almirola" points_eligible="true" id="e128a081-a2e8-4809-8038-8c936049bf7c"/>
      <pit-stops>
        <pit-stop sequence="1" lap="0" leader_lap="0" positions_gained="0" in_time="0.0" out_time="0.0"/>
        <pit-stop sequence="2" lap="71" leader_lap="71" positions_gained="-1" in_time="1570.87" out_time="1618.573"/>
        <pit-stop sequence="3" lap="72" leader_lap="72" positions_gained="0" in_time="1618.573" out_time="0.0"/>
        <pit-stop sequence="4" lap="108" leader_lap="108" positions_gained="-3" in_time="2558.843" out_time="2607.387"/>
        <pit-stop sequence="5" lap="134" leader_lap="134" positions_gained="1" in_time="3637.655" out_time="3685.357"/>
        <pit-stop sequence="6" lap="265" leader_lap="266" positions_gained="1" in_time="6875.668" out_time="6925.059"/>
        <pit-stop sequence="7" lap="296" leader_lap="297" positions_gained="0" in_time="8018.55" out_time="8070.06"/>
        <pit-stop sequence="8" lap="335" leader_lap="335" positions_gained="1" in_time="9125.552" out_time="9173.025"/>
        <pit-stop sequence="9" lap="393" leader_lap="393" positions_gained="1" in_time="10538.039" out_time="10585.196"/>
        <pit-stop sequence="10" lap="420" leader_lap="420" positions_gained="-1" in_time="11555.281" out_time="11621.679"/>
        <pit-stop sequence="11" lap="421" leader_lap="422" positions_gained="0" in_time="11621.679" out_time="0.0"/>
        <pit-stop sequence="12" lap="432" leader_lap="432" positions_gained="1" in_time="11987.558" out_time="12036.232"/>
        <pit-stop sequence="13" lap="500" leader_lap="500" positions_gained="0" in_time="13612.687" out_time="0.0"/>
      </pit-stops>
    </result>
    <result start_position="22" position="19" status="running" pit_stops="13" best_lap="4" best_lap_speed="91.531" best_lap_time="20.688" elapsed_time="13516.999" fastest_laps="1" avg_position="21.78" avg_speed="70.045" passes_made="45" quality_passes="5" times_passed="58" passing_differential="-13" last_lap_speed="87.239" last_lap_time="21.706" avg_restart_speed="88.132" points="18" bonus_points="0" penalty_points="0" stage_1_points="0" stage_2_points="0" money="0.0" laps_led="0" times_led="0" laps_completed="500">
      <car number="27" sponsors="Menard's" crew_chief="Matt Borland" id="021d546c-56ee-4399-bc87-00a526bae83d">
        <manufacturer id="dbf04b7a-c4a2-4cff-9dd0-cf1977fc446e" name="Chevrolet"/>
        <owner id="b28b1f53-bdee-4c44-97fb-bb1fd0ea4a8b" name="Richard Childress"/>
        <team id="ffd3ba10-57f2-4bb8-9aaf-7c64b1ba793a" name="Richard Childress Racing">
          <owner id="84e3b257-75b1-40ef-8774-cfb53fab90e9" name="Richard Childress"/>
        </team>
      </car>
      <driver first_name="Paul" last_name="Menard" full_name="Paul Menard" points_eligible="true" id="cb239c48-8ccb-4043-a221-531b0da78765"/>
      <pit-stops>
        <pit-stop sequence="1" lap="0" leader_lap="0" positions_gained="0" in_time="0.0" out_time="0.0"/>
        <pit-stop sequence="2" lap="71" leader_lap="71" positions_gained="0" in_time="1575.319" out_time="1624.25"/>
        <pit-stop sequence="3" lap="108" leader_lap="108" positions_gained="10" in_time="2561.536" out_time="2601.446"/>
        <pit-stop sequence="4" lap="134" leader_lap="134" positions_gained="7" in_time="3636.125" out_time="3677.08"/>
        <pit-stop sequence="5" lap="265" leader_lap="266" positions_gained="0" in_time="6879.573" out_time="6930.954"/>
        <pit-stop sequence="6" lap="289" leader_lap="290" positions_gained="0" in_time="7742.041" out_time="7791.567"/>
        <pit-stop sequence="7" lap="310" leader_lap="311" positions_gained="-1" in_time="8508.446" out_time="8557.035"/>
        <pit-stop sequence="8" lap="336" leader_lap="337" positions_gained="0" in_time="9188.621" out_time="9237.94"/>
        <pit-stop sequence="9" lap="407" leader_lap="407" positions_gained="1" in_time="11027.173" out_time="11076.357"/>
        <pit-stop sequence="10" lap="420" leader_lap="420" positions_gained="-1" in_time="11546.495" out_time="11617.96"/>
        <pit-stop sequence="11" lap="422" leader_lap="423" positions_gained="0" in_time="11658.996" out_time="11719.2"/>
        <pit-stop sequence="12" lap="432" leader_lap="432" positions_gained="-2" in_time="11990.234" out_time="12059.637"/>
        <pit-stop sequence="13" lap="500" leader_lap="500" positions_gained="0" in_time="13603.73" out_time="0.0"/>
      </pit-stops>
    </result>
    <result start_position="9" position="20" status="running" pit_stops="12" best_lap="4" best_lap_speed="92.619" best_lap_time="20.445" elapsed_time="13518.969" fastest_laps="2" avg_position="18.232" avg_speed="70.035" passes_made="45" quality_passes="19" times_passed="51" passing_differential="-6" last_lap_speed="86.414" last_lap_time="21.913" avg_restart_speed="88.425" points="17" bonus_points="0" penalty_points="0" stage_1_points="0" stage_2_points="0" money="0.0" laps_led="0" times_led="0" laps_completed="500">
      <car number="4" sponsors="Busch Beer/Jimmy Johns/Mobil 1" crew_chief="Rodney Childers" id="6713b606-f0b9-4b23-bcf3-9f2e4e9a91a7">
        <manufacturer id="12844047-ab59-43ca-ab6c-c10d54931715" name="Ford"/>
        <owner id="f605ad11-b0a3-423b-a1f0-220cfa224968" name="Tony Stewart"/>
        <team id="876a07ff-ff53-4f23-9528-6d9795270244" name="Stewart Haas Racing">
          <owner id="160c7b9e-b198-4b4d-9000-bcdc1a094cee" name="Tony Stewart"/>
        </team>
      </car>
      <driver first_name="Kevin" last_name="Harvick" full_name="Kevin Harvick" points_eligible="true" id="9d18716c-fd73-48d4-b3da-44228c767b84"/>
      <pit-stops>
        <pit-stop sequence="1" lap="0" leader_lap="0" positions_gained="0" in_time="0.0" out_time="0.0"/>
        <pit-stop sequence="2" lap="71" leader_lap="71" positions_gained="3" in_time="1567.865" out_time="1614.172"/>
        <pit-stop sequence="3" lap="108" leader_lap="108" positions_gained="-4" in_time="2555.099" out_time="2602.903"/>
        <pit-stop sequence="4" lap="134" leader_lap="134" positions_gained="1" in_time="3635.683" out_time="3682.149"/>
        <pit-stop sequence="5" lap="265" leader_lap="266" positions_gained="-1" in_time="6876.251" out_time="6928.118"/>
        <pit-stop sequence="6" lap="279" leader_lap="280" positions_gained="0" in_time="7426.638" out_time="7473.534"/>
        <pit-stop sequence="7" lap="310" leader_lap="311" positions_gained="2" in_time="8509.548" out_time="8556.109"/>
        <pit-stop sequence="8" lap="335" leader_lap="336" positions_gained="0" in_time="9171.607" out_time="9219.836"/>
        <pit-stop sequence="9" lap="393" leader_lap="394" positions_gained="0" in_time="10584.995" out_time="10637.235"/>
        <pit-stop sequence="10" lap="408" leader_lap="409" positions_gained="0" in_time="11086.02" out_time="11134.609"/>
        <pit-stop sequence="11" lap="432" leader_lap="432" positions_gained="-3" in_time="11983.665" out_time="12049.598"/>
        <pit-stop sequence="12" lap="500" leader_lap="500" positions_gained="0" in_time="13634.136" out_time="0.0"/>
      </pit-stops>
    </result>
    <result start_position="31" position="21" status="running" pit_stops="9" best_lap="8" best_lap_speed="91.531" best_lap_time="20.688" elapsed_time="13502.347" fastest_laps="0" avg_position="23.426" avg_speed="69.981" passes_made="37" quality_passes="10" times_passed="43" passing_differential="-6" last_lap_speed="87.634" last_lap_time="21.608" avg_restart_speed="87.795" points="16" bonus_points="0" penalty_points="0" stage_1_points="0" stage_2_points="0" money="0.0" laps_led="0" times_led="0" laps_completed="499">
      <car number="72" sponsors="Florida Lottery/RTIC Coolers/Rinnai/Carolina Skiff/Standard Plumbing Supply" crew_chief="Frank Kerr" id="b5b7fdaa-bc33-4076-8428-2ac317f9f2d8">
        <manufacturer id="12844047-ab59-43ca-ab6c-c10d54931715" name="Ford"/>
        <owner id="fe6c0a50-06f5-4b9a-8615-e243c9695c8a" name="Mark Smith"/>
        <team id="1fcfb1ff-77e7-44e3-824a-d0506e270b54" name="TriStar Motorsports">
        </team>
      </car>
      <driver first_name="Cole" last_name="Whitt" full_name="Cole Whitt" points_eligible="true" id="30180a89-d256-4ab3-aa14-cd5aaab61737"/>
      <pit-stops>
        <pit-stop sequence="1" lap="0" leader_lap="0" positions_gained="0" in_time="0.0" out_time="0.0"/>
        <pit-stop sequence="2" lap="109" leader_lap="109" positions_gained="0" in_time="2611.208" out_time="2677.576"/>
        <pit-stop sequence="3" lap="124" leader_lap="125" positions_gained="-2" in_time="3196.043" out_time="3255.233"/>
        <pit-stop sequence="4" lap="265" leader_lap="266" positions_gained="-4" in_time="6873.093" out_time="6925.648"/>
        <pit-stop sequence="5" lap="310" leader_lap="311" positions_gained="-1" in_time="8509.014" out_time="8560.951"/>
        <pit-stop sequence="6" lap="335" leader_lap="336" positions_gained="0" in_time="9171.149" out_time="9226.425"/>
        <pit-stop sequence="7" lap="407" leader_lap="408" positions_gained="0" in_time="11078.391" out_time="11129.437"/>
        <pit-stop sequence="8" lap="431" leader_lap="432" positions_gained="0" in_time="11987.046" out_time="12039.227"/>
        <pit-stop sequence="9" lap="499" leader_lap="500" positions_gained="0" in_time="13543.83" out_time="0.0"/>
      </pit-stops>
    </result>
    <result start_position="23" position="22" status="running" pit_stops="11" best_lap="428" best_lap_speed="91.043" best_lap_time="20.799" elapsed_time="13518.288" fastest_laps="1" avg_position="22.834" avg_speed="69.898" passes_made="43" quality_passes="2" times_passed="52" passing_differential="-9" last_lap_speed="86.116" last_lap_time="21.989" avg_restart_speed="88.094" points="15" bonus_points="0" penalty_points="0" stage_1_points="0" stage_2_points="0" money="0.0" laps_led="0" times_led="0" laps_completed="499">
      <car number="13" sponsors="GEICO/Twisted Tea" crew_chief="Bootie Barker" id="fe0dffc0-6808-4372-8b4c-6c91761a0748">
        <manufacturer id="dbf04b7a-c4a2-4cff-9dd0-cf1977fc446e" name="Chevrolet"/>
        <owner id="55059110-7836-4319-b778-473247e7eb05" name="Bob Germain Jr."/>
        <team id="5f6dc3c2-f6a6-44e9-a9a0-90d73570de24" name="Germain Racing">
        </team>
      </car>
      <driver first_name="Ty" last_name="Dillon" full_name="Ty Dillon" points_eligible="true" id="bfcb8d32-fab0-4bfa-be14-cf9466e1d886"/>
      <pit-stops>
        <pit-stop sequence="1" lap="0" leader_lap="0" positions_gained="0" in_time="0.0" out_time="0.0"/>
        <pit-stop sequence="2" lap="72" leader_lap="72" positions_gained="1" in_time="1621.779" out_time="1672.305"/>
        <pit-stop sequence="3" lap="134" leader_lap="134" positions_gained="-2" in_time="3635.196" out_time="3683.161"/>
        <pit-stop sequence="4" lap="262" leader_lap="263" positions_gained="0" in_time="6697.503" out_time="6760.938"/>
        <pit-stop sequence="5" lap="289" leader_lap="290" positions_gained="0" in_time="7743.671" out_time="7796.919"/>
        <pit-stop sequence="6" lap="335" leader_lap="336" positions_gained="0" in_time="9170.09" out_time="9218.917"/>
        <pit-stop sequence="7" lap="393" leader_lap="394" positions_gained="0" in_time="10584.161" out_time="10633.465"/>
        <pit-stop sequence="8" lap="420" leader_lap="421" positions_gained="0" in_time="11601.312" out_time="11655.459"/>
        <pit-stop sequence="9" lap="421" leader_lap="423" positions_gained="0" in_time="11663.609" out_time="11707.712"/>
        <pit-stop sequence="10" lap="422" leader_lap="424" positions_gained="0" in_time="11715.68" out_time="11758.5"/>
        <pit-stop sequence="11" lap="499" leader_lap="500" positions_gained="0" in_time="13628.774" out_time="0.0"/>
      </pit-stops>
    </result>
    <result start_position="29" position="23" status="running" pit_stops="11" best_lap="8" best_lap_speed="91.289" best_lap_time="20.743" elapsed_time="13519.777" fastest_laps="0" avg_position="22.062" avg_speed="69.891" passes_made="76" quality_passes="24" times_passed="82" passing_differential="-6" last_lap_speed="87.134" last_lap_time="21.732" avg_restart_speed="88.033" points="14" bonus_points="0" penalty_points="0" stage_1_points="0" stage_2_points="0" money="0.0" laps_led="0" times_led="0" laps_completed="499">
      <car number="10" sponsors="Aspen Dental/TaxACT/Mobil1/Code 3 Associates" crew_chief="Billy Scott" id="2e3b8a4c-5c1c-401d-98b2-7c92bcab23e5">
        <manufacturer id="12844047-ab59-43ca-ab6c-c10d54931715" name="Ford"/>
        <owner id="f605ad11-b0a3-423b-a1f0-220cfa224968" name="Tony Stewart"/>
        <team id="876a07ff-ff53-4f23-9528-6d9795270244" name="Stewart Haas Racing">
          <owner id="160c7b9e-b198-4b4d-9000-bcdc1a094cee" name="Tony Stewart"/>
        </team>
      </car>
      <driver first_name="Danica" last_name="Patrick" full_name="Danica Patrick" points_eligible="true" id="262c7b0f-fab8-4d5e-854c-7d54d039b994"/>
      <pit-stops>
        <pit-stop sequence="1" lap="0" leader_lap="0" positions_gained="0" in_time="0.0" out_time="0.0"/>
        <pit-stop sequence="2" lap="71" leader_lap="72" positions_gained="-3" in_time="1615.911" out_time="1672.903"/>
        <pit-stop sequence="3" lap="108" leader_lap="109" positions_gained="3" in_time="2607.779" out_time="2657.001"/>
        <pit-stop sequence="4" lap="124" leader_lap="125" positions_gained="2" in_time="3198.06" out_time="3249.936"/>
        <pit-stop sequence="5" lap="265" leader_lap="266" positions_gained="0" in_time="6874.779" out_time="6924.082"/>
        <pit-stop sequence="6" lap="289" leader_lap="290" positions_gained="0" in_time="7739.062" out_time="7789.656"/>
        <pit-stop sequence="7" lap="310" leader_lap="310" positions_gained="0" in_time="8459.494" out_time="8509.686"/>
        <pit-stop sequence="8" lap="335" leader_lap="335" positions_gained="0" in_time="9126.001" out_time="9173.978"/>
        <pit-stop sequence="9" lap="393" leader_lap="393" positions_gained="0" in_time="10538.731" out_time="10590.471"/>
        <pit-stop sequence="10" lap="420" leader_lap="421" positions_gained="0" in_time="11604.289" out_time="11659.51"/>
        <pit-stop sequence="11" lap="499" leader_lap="500" positions_gained="0" in_time="13624.535" out_time="0.0"/>
      </pit-stops>
    </result>
    <result start_position="34" position="24" status="running" pit_stops="11" best_lap="118" best_lap_speed="91.319" best_lap_time="20.736" elapsed_time="13505.325" fastest_laps="2" avg_position="27.984" avg_speed="69.825" passes_made="33" quality_passes="0" times_passed="29" passing_differential="4" last_lap_speed="87.61" last_lap_time="21.614" avg_restart_speed="88.06" points="13" bonus_points="0" penalty_points="0" stage_1_points="0" stage_2_points="0" money="0.0" laps_led="0" times_led="0" laps_completed="498">
      <car number="38" sponsors="Camping World/Good Sam/Jacob/Juice Battery" crew_chief="Derrick Finley" id="122dc137-45ec-41a0-9cf4-c447c34330b4">
        <manufacturer id="12844047-ab59-43ca-ab6c-c10d54931715" name="Ford"/>
        <owner id="69e98f6f-ffa3-4b40-832a-33b262151bba" name="Brad Jenkins"/>
        <team id="bd38dfec-bb97-4f29-b032-cc6f0c77dfe6" name="Front Row Motorsports">
        </team>
      </car>
      <driver first_name="David" last_name="Ragan" full_name="David Ragan" points_eligible="true" id="25884070-3ded-4fdc-9370-d09428ac95e4"/>
      <pit-stops>
        <pit-stop sequence="1" lap="0" leader_lap="0" positions_gained="0" in_time="0.0" out_time="0.0"/>
        <pit-stop sequence="2" lap="71" leader_lap="72" positions_gained="2" in_time="1616.452" out_time="1666.473"/>
        <pit-stop sequence="3" lap="108" leader_lap="109" positions_gained="1" in_time="2608.895" out_time="2659.107"/>
        <pit-stop sequence="4" lap="114" leader_lap="116" positions_gained="0" in_time="2934.67" out_time="2972.789"/>
        <pit-stop sequence="5" lap="134" leader_lap="135" positions_gained="0" in_time="3689.494" out_time="3736.901"/>
        <pit-stop sequence="6" lap="264" leader_lap="266" positions_gained="0" in_time="6877.933" out_time="6928.683"/>
        <pit-stop sequence="7" lap="265" leader_lap="267" positions_gained="0" in_time="6928.683" out_time="0.0"/>
        <pit-stop sequence="8" lap="288" leader_lap="290" positions_gained="0" in_time="7741.372" out_time="7789.029"/>
        <pit-stop sequence="9" lap="334" leader_lap="336" positions_gained="0" in_time="9170.632" out_time="9218.892"/>
        <pit-stop sequence="10" lap="407" leader_lap="408" positions_gained="0" in_time="11081.46" out_time="11130.432"/>
        <pit-stop sequence="11" lap="498" leader_lap="500" positions_gained="0" in_time="13558.922" out_time="0.0"/>
      </pit-stops>
    </result>
    <result start_position="7" position="25" status="running" pit_stops="14" best_lap="144" best_lap_speed="92.213" best_lap_time="20.535" elapsed_time="13517.766" fastest_laps="4" avg_position="14.778" avg_speed="69.761" passes_made="62" quality_passes="35" times_passed="51" passing_differential="11" last_lap_speed="85.843" last_lap_time="22.059" avg_restart_speed="88.547" points="22" bonus_points="10" penalty_points="0" stage_1_points="4" stage_2_points="6" money="0.0" laps_led="0" times_led="0" laps_completed="498">
      <car number="21" sponsors="Motorcraft/Quick Lane/SKF" crew_chief="Jeremy Bullins" id="df4ce303-5e1b-4f90-bdd0-1e768780109c">
        <manufacturer id="12844047-ab59-43ca-ab6c-c10d54931715" name="Ford"/>
        <owner id="90731d44-8da2-45bd-a8a7-41107fc46e03" name="Glen Wood"/>
        <team id="0dd8fd36-8bb1-4930-bfdc-d0c6be3b1a13" name="Wood Brothers">
          <owner id="9fe6c239-ccda-43d0-9bb3-7c72606bf210" name="Wood Brothers"/>
        </team>
      </car>
      <driver first_name="Ryan" last_name="Blaney" full_name="Ryan Blaney" points_eligible="true" id="67948099-4196-4e1b-ae9e-b437aa99000a"/>
      <pit-stops>
        <pit-stop sequence="1" lap="0" leader_lap="0" positions_gained="0" in_time="0.0" out_time="0.0"/>
        <pit-stop sequence="2" lap="71" leader_lap="71" positions_gained="-12" in_time="1564.876" out_time="1618.799"/>
        <pit-stop sequence="3" lap="108" leader_lap="108" positions_gained="-4" in_time="2554.462" out_time="2602.397"/>
        <pit-stop sequence="4" lap="265" leader_lap="265" positions_gained="-10" in_time="6823.088" out_time="6882.281"/>
        <pit-stop sequence="5" lap="279" leader_lap="279" positions_gained="0" in_time="7367.813" out_time="7415.532"/>
        <pit-stop sequence="6" lap="290" leader_lap="290" positions_gained="4" in_time="7740.316" out_time="7790.824"/>
        <pit-stop sequence="7" lap="291" leader_lap="292" positions_gained="0" in_time="7802.142" out_time="7857.723"/>
        <pit-stop sequence="8" lap="297" leader_lap="297" positions_gained="1" in_time="8024.471" out_time="8073.705"/>
        <pit-stop sequence="9" lap="304" leader_lap="304" positions_gained="0" in_time="8288.814" out_time="8337.101"/>
        <pit-stop sequence="10" lap="309" leader_lap="311" positions_gained="0" in_time="8502.895" out_time="8570.615"/>
        <pit-stop sequence="11" lap="334" leader_lap="336" positions_gained="0" in_time="9172.249" out_time="9242.346"/>
        <pit-stop sequence="12" lap="406" leader_lap="408" positions_gained="0" in_time="11079.869" out_time="11133.401"/>
        <pit-stop sequence="13" lap="419" leader_lap="421" positions_gained="0" in_time="11598.669" out_time="11650.67"/>
        <pit-stop sequence="14" lap="498" leader_lap="500" positions_gained="0" in_time="13610.73" out_time="0.0"/>
      </pit-stops>
    </result>
    <result start_position="26" position="26" status="running" pit_stops="9" best_lap="8" best_lap_speed="91.214" best_lap_time="20.76" elapsed_time="13502.022" fastest_laps="0" avg_position="28.134" avg_speed="69.702" passes_made="25" quality_passes="0" times_passed="29" passing_differential="-4" last_lap_speed="86.612" last_lap_time="21.863" avg_restart_speed="87.757" points="11" bonus_points="0" penalty_points="0" stage_1_points="0" stage_2_points="0" money="0.0" laps_led="0" times_led="0" laps_completed="497">
      <car number="95" sponsors="KLove Radio/WRL Contractors" crew_chief="Todd Parrott" id="eec39cd8-aad1-45cb-b550-4bec979193d9">
        <manufacturer id="dbf04b7a-c4a2-4cff-9dd0-cf1977fc446e" name="Chevrolet"/>
        <owner id="29740c17-d3fa-43f2-b44f-0660b3bd3dfc" name="Bob Leavine"/>
        <team id="2325ec83-aa71-445e-aaa2-d92997a1da89" name="Leavine Family Racing">
          <owner id="0a6a3e6d-809d-4079-adf5-0ff629ef8aa8" name="Bob Leavine"/>
        </team>
      </car>
      <driver first_name="Michael" last_name="McDowell" full_name="Michael McDowell" points_eligible="true" id="96fdd8d7-3776-42b8-baf2-6b4e2cf2d83d"/>
      <pit-stops>
        <pit-stop sequence="1" lap="0" leader_lap="0" positions_gained="0" in_time="0.0" out_time="0.0"/>
        <pit-stop sequence="2" lap="71" leader_lap="72" positions_gained="-1" in_time="1615.269" out_time="1666.899"/>
        <pit-stop sequence="3" lap="108" leader_lap="109" positions_gained="3" in_time="2609.578" out_time="2658.305"/>
        <pit-stop sequence="4" lap="134" leader_lap="135" positions_gained="0" in_time="3688.764" out_time="3736.757"/>
        <pit-stop sequence="5" lap="264" leader_lap="266" positions_gained="0" in_time="6877.489" out_time="6926.997"/>
        <pit-stop sequence="6" lap="334" leader_lap="336" positions_gained="0" in_time="9172.791" out_time="9220.671"/>
        <pit-stop sequence="7" lap="406" leader_lap="408" positions_gained="0" in_time="11081.032" out_time="11128.63"/>
        <pit-stop sequence="8" lap="430" leader_lap="432" positions_gained="0" in_time="11988.02" out_time="12036.778"/>
        <pit-stop sequence="9" lap="497" leader_lap="500" positions_gained="0" in_time="13537.916" out_time="0.0"/>
      </pit-stops>
    </result>
    <result start_position="27" position="27" status="running" pit_stops="9" best_lap="8" best_lap_speed="90.703" best_lap_time="20.877" elapsed_time="13505.072" fastest_laps="0" avg_position="29.632" avg_speed="69.686" passes_made="22" quality_passes="0" times_passed="36" passing_differential="-14" last_lap_speed="87.002" last_lap_time="21.765" avg_restart_speed="87.156" points="10" bonus_points="0" penalty_points="0" stage_1_points="0" stage_2_points="0" money="0.0" laps_led="0" times_led="0" laps_completed="497">
      <car number="34" sponsors="Love's/CXS Play It Safe/Starkey Hearing Foundation" crew_chief="Donnie Wingo" id="89e035f0-87f6-4835-ac58-8b7da32de4a4">
        <manufacturer id="12844047-ab59-43ca-ab6c-c10d54931715" name="Ford"/>
        <owner id="c81a723c-a430-4be5-969f-5fbf21c1d519" name="Bob Jenkins"/>
        <team id="bd38dfec-bb97-4f29-b032-cc6f0c77dfe6" name="Front Row Motorsports">
        </team>
      </car>
      <driver first_name="Landon" last_name="Cassill" full_name="Landon Cassill" points_eligible="true" id="f07507f1-0a84-4b90-929d-7389dc5baab4"/>
      <pit-stops>
        <pit-stop sequence="1" lap="0" leader_lap="0" positions_gained="0" in_time="0.0" out_time="0.0"/>
        <pit-stop sequence="2" lap="108" leader_lap="109" positions_gained="0" in_time="2603.086" out_time="2654.529"/>
        <pit-stop sequence="3" lap="134" leader_lap="135" positions_gained="-1" in_time="3691.463" out_time="3752.037"/>
        <pit-stop sequence="4" lap="264" leader_lap="266" positions_gained="0" in_time="6879.069" out_time="6929.203"/>
        <pit-stop sequence="5" lap="288" leader_lap="290" positions_gained="0" in_time="7742.727" out_time="7793.592"/>
        <pit-stop sequence="6" lap="334" leader_lap="336" positions_gained="0" in_time="9173.902" out_time="9223.409"/>
        <pit-stop sequence="7" lap="406" leader_lap="408" positions_gained="0" in_time="11082.083" out_time="11131.39"/>
        <pit-stop sequence="8" lap="430" leader_lap="432" positions_gained="0" in_time="11989.634" out_time="12040.997"/>
        <pit-stop sequence="9" lap="497" leader_lap="500" positions_gained="0" in_time="13559.153" out_time="0.0"/>
      </pit-stops>
    </result>
    <result start_position="35" position="28" status="running" pit_stops="9" best_lap="8" best_lap_speed="90.759" best_lap_time="20.864" elapsed_time="13507.119" fastest_laps="0" avg_position="31.682" avg_speed="69.536" passes_made="15" quality_passes="0" times_passed="18" passing_differential="-3" last_lap_speed="86.874" last_lap_time="21.797" avg_restart_speed="87.292" points="9" bonus_points="0" penalty_points="0" stage_1_points="0" stage_2_points="0" money="0.0" laps_led="0" times_led="0" laps_completed="496">
      <car number="83" sponsors="Dustless Blasters/JAS Expedited Trucking/Bubba Burger" crew_chief="Ryan Dubois" id="fbf7afde-74a4-4ea4-b02e-d2ad600c75ee">
        <manufacturer id="73364deb-a012-4625-b759-db6a236797e3" name="Toyota"/>
        <owner id="a8c6c52b-0e8d-4891-b8f8-7d44ee6d4923" name="Ron Devine"/>
        <team id="ca72b90b-6d4e-4c24-bdea-cca1d04741b1" name="BK Racing">
        </team>
      </car>
      <driver first_name="Corey" last_name="LaJoie" full_name="Corey LaJoie" points_eligible="true" id="68b9a7ed-c810-4c0d-a330-7a99b90c2587"/>
      <pit-stops>
        <pit-stop sequence="1" lap="0" leader_lap="0" positions_gained="0" in_time="0.0" out_time="0.0"/>
        <pit-stop sequence="2" lap="108" leader_lap="109" positions_gained="-3" in_time="2606.547" out_time="2660.234"/>
        <pit-stop sequence="3" lap="123" leader_lap="125" positions_gained="0" in_time="3194.672" out_time="3236.658"/>
        <pit-stop sequence="4" lap="134" leader_lap="135" positions_gained="2" in_time="3691.918" out_time="3741.54"/>
        <pit-stop sequence="5" lap="263" leader_lap="266" positions_gained="0" in_time="6873.673" out_time="6923.428"/>
        <pit-stop sequence="6" lap="276" leader_lap="279" positions_gained="0" in_time="7376.699" out_time="7431.888"/>
        <pit-stop sequence="7" lap="333" leader_lap="336" positions_gained="0" in_time="9174.568" out_time="9229.67"/>
        <pit-stop sequence="8" lap="405" leader_lap="408" positions_gained="0" in_time="11082.805" out_time="11139.327"/>
        <pit-stop sequence="9" lap="496" leader_lap="500" positions_gained="0" in_time="13563.339" out_time="0.0"/>
      </pit-stops>
    </result>
    <result start_position="37" position="29" status="running" pit_stops="10" best_lap="9" best_lap_speed="90.92" best_lap_time="20.827" elapsed_time="13518.533" fastest_laps="0" avg_position="31.586" avg_speed="69.337" passes_made="24" quality_passes="0" times_passed="25" passing_differential="-1" last_lap_speed="85.924" last_lap_time="22.038" avg_restart_speed="87.52" points="8" bonus_points="0" penalty_points="0" stage_1_points="0" stage_2_points="0" money="0.0" laps_led="0" times_led="0" laps_completed="495">
      <car number="23" sponsors="Best Home Furnishing/Dr. Pepper/Schluter Systems/Sunfrog.com" crew_chief="Patrick Donahue" id="4a56a3be-1d91-434e-a403-24b3206573b7">
        <manufacturer id="73364deb-a012-4625-b759-db6a236797e3" name="Toyota"/>
        <owner id="a8c6c52b-0e8d-4891-b8f8-7d44ee6d4923" name="Ron Devine"/>
        <team id="ca72b90b-6d4e-4c24-bdea-cca1d04741b1" name="BK Racing">
        </team>
      </car>
      <driver first_name="Gray" last_name="Gaulding" full_name="Gray Gaulding" points_eligible="true" id="6e5a779b-11fa-46bf-bfc9-51efedfe66c4"/>
      <pit-stops>
        <pit-stop sequence="1" lap="0" leader_lap="0" positions_gained="0" in_time="0.0" out_time="0.0"/>
        <pit-stop sequence="2" lap="108" leader_lap="109" positions_gained="-6" in_time="2605.323" out_time="2673.283"/>
        <pit-stop sequence="3" lap="111" leader_lap="113" positions_gained="0" in_time="2785.218" out_time="2832.274"/>
        <pit-stop sequence="4" lap="123" leader_lap="125" positions_gained="0" in_time="3195.445" out_time="3235.998"/>
        <pit-stop sequence="5" lap="134" leader_lap="135" positions_gained="-1" in_time="3690.871" out_time="3746.164"/>
        <pit-stop sequence="6" lap="263" leader_lap="266" positions_gained="0" in_time="6872.518" out_time="6925.124"/>
        <pit-stop sequence="7" lap="307" leader_lap="311" positions_gained="0" in_time="8517.277" out_time="8580.176"/>
        <pit-stop sequence="8" lap="332" leader_lap="336" positions_gained="0" in_time="9173.4" out_time="9225.535"/>
        <pit-stop sequence="9" lap="404" leader_lap="408" positions_gained="0" in_time="11083.536" out_time="11136.092"/>
        <pit-stop sequence="10" lap="495" leader_lap="500" positions_gained="0" in_time="13617.224" out_time="0.0"/>
      </pit-stops>
    </result>
    <result start_position="12" position="30" status="running" pit_stops="12" best_lap="80" best_lap_speed="92.389" best_lap_time="20.496" elapsed_time="13512.595" fastest_laps="8" avg_position="14.686" avg_speed="69.087" passes_made="56" quality_passes="36" times_passed="50" passing_differential="6" last_lap_speed="83.985" last_lap_time="22.547" avg_restart_speed="88.359" points="16" bonus_points="9" penalty_points="0" stage_1_points="9" stage_2_points="0" money="0.0" laps_led="24" times_led="2" laps_completed="493">
      <car number="11" sponsors="FedEx/Sport Clips/Hisense" crew_chief="Mike Wheeler" id="a4fca4d9-9ffa-4b72-8673-f851f6fd9677">
        <manufacturer id="73364deb-a012-4625-b759-db6a236797e3" name="Toyota"/>
        <owner id="1ddb24a4-3c7e-4ea5-a5e3-cfb8d405336e" name="J.D. Gibbs"/>
        <team id="b30dee06-c437-4e76-8b9c-8b850d52ce21" name="Joe Gibbs Racing">
        </team>
      </car>
      <driver first_name="Denny" last_name="Hamlin" full_name="Denny Hamlin" points_eligible="true" id="cb9d6f49-0044-4305-be9a-22d428e52c95"/>
      <pit-stops>
        <pit-stop sequence="1" lap="0" leader_lap="0" positions_gained="0" in_time="0.0" out_time="0.0"/>
        <pit-stop sequence="2" lap="71" leader_lap="71" positions_gained="2" in_time="1566.947" out_time="1613.175"/>
        <pit-stop sequence="3" lap="108" leader_lap="108" positions_gained="0" in_time="2549.812" out_time="2589.971"/>
        <pit-stop sequence="4" lap="134" leader_lap="134" positions_gained="-3" in_time="3631.252" out_time="3677.961"/>
        <pit-stop sequence="5" lap="265" leader_lap="265" positions_gained="2" in_time="6832.496" out_time="6878.45"/>
        <pit-stop sequence="6" lap="279" leader_lap="279" positions_gained="0" in_time="7366.794" out_time="7413.637"/>
        <pit-stop sequence="7" lap="290" leader_lap="290" positions_gained="-2" in_time="7737.413" out_time="7803.993"/>
        <pit-stop sequence="8" lap="297" leader_lap="297" positions_gained="-2" in_time="8020.811" out_time="8086.79"/>
        <pit-stop sequence="9" lap="393" leader_lap="393" positions_gained="-4" in_time="10535.724" out_time="10585.943"/>
        <pit-stop sequence="10" lap="418" leader_lap="419" positions_gained="0" in_time="11461.642" out_time="11679.736"/>
        <pit-stop sequence="11" lap="427" leader_lap="432" positions_gained="0" in_time="11951.615" out_time="12100.235"/>
        <pit-stop sequence="12" lap="493" leader_lap="500" positions_gained="0" in_time="13599.991" out_time="0.0"/>
      </pit-stops>
      <laps-led>
        <lead sequence="1" start_lap="89" end_lap="108"/>
        <lead sequence="2" start_lap="337" end_lap="340"/>
      </laps-led>
    </result>
    <result start_position="32" position="31" status="running" pit_stops="13" best_lap="4" best_lap_speed="90.382" best_lap_time="20.951" elapsed_time="13511.135" fastest_laps="0" avg_position="32.822" avg_speed="68.954" passes_made="21" quality_passes="0" times_passed="25" passing_differential="-4" last_lap_speed="87.154" last_lap_time="21.727" avg_restart_speed="87.253" points="6" bonus_points="0" penalty_points="0" stage_1_points="0" stage_2_points="0" money="0.0" laps_led="0" times_led="0" laps_completed="492">
      <car number="15" sponsors="Aaron's/Maid's" crew_chief="Mark Hillman" id="49118217-dcc7-47f9-a1c5-5505e6835d15">
        <manufacturer id="dbf04b7a-c4a2-4cff-9dd0-cf1977fc446e" name="Chevrolet"/>
        <owner id="767fd447-89f5-4f9b-9cef-90805aec1aed" name="Jay Robinson"/>
        <team id="ab68c67f-7f5f-4c26-87d1-5cd7d0fc4c25" name="Premium Motorsports">
        </team>
      </car>
      <driver first_name="Reed" last_name="Sorenson" full_name="Reed Sorenson" points_eligible="true" id="1a618e86-838d-4983-9b52-011a67cccf7a"/>
      <pit-stops>
        <pit-stop sequence="1" lap="0" leader_lap="0" positions_gained="0" in_time="0.0" out_time="0.0"/>
        <pit-stop sequence="2" lap="71" leader_lap="72" positions_gained="1" in_time="1618.093" out_time="1671.275"/>
        <pit-stop sequence="3" lap="108" leader_lap="109" positions_gained="1" in_time="2610.328" out_time="2668.542"/>
        <pit-stop sequence="4" lap="111" leader_lap="113" positions_gained="0" in_time="2784.138" out_time="2829.005"/>
        <pit-stop sequence="5" lap="134" leader_lap="135" positions_gained="0" in_time="3692.647" out_time="3752.963"/>
        <pit-stop sequence="6" lap="263" leader_lap="266" positions_gained="0" in_time="6874.304" out_time="6934.996"/>
        <pit-stop sequence="7" lap="287" leader_lap="290" positions_gained="0" in_time="7745.346" out_time="7788.685"/>
        <pit-stop sequence="8" lap="308" leader_lap="311" positions_gained="0" in_time="8513.777" out_time="8567.965"/>
        <pit-stop sequence="9" lap="330" leader_lap="336" positions_gained="0" in_time="9141.591" out_time="9233.995"/>
        <pit-stop sequence="10" lap="331" leader_lap="338" positions_gained="0" in_time="9246.025" out_time="9323.172"/>
        <pit-stop sequence="11" lap="401" leader_lap="409" positions_gained="0" in_time="11084.79" out_time="11143.952"/>
        <pit-stop sequence="12" lap="414" leader_lap="421" positions_gained="0" in_time="11603.579" out_time="11656.511"/>
        <pit-stop sequence="13" lap="492" leader_lap="500" positions_gained="0" in_time="13587.806" out_time="0.0"/>
      </pit-stops>
    </result>
    <result start_position="19" position="32" status="running" pit_stops="10" best_lap="8" best_lap_speed="91.408" best_lap_time="20.716" elapsed_time="13510.786" fastest_laps="4" avg_position="33.774" avg_speed="68.536" passes_made="32" quality_passes="0" times_passed="29" passing_differential="3" last_lap_speed="87.432" last_lap_time="21.658" avg_restart_speed="84.992" points="5" bonus_points="0" penalty_points="0" stage_1_points="0" stage_2_points="0" money="0.0" laps_led="0" times_led="0" laps_completed="489">
      <car number="19" sponsors="ARRIS/Stanley/Subway/Juniper" crew_chief="Dave Rogers" id="1e8fcd69-e12e-4fb4-8dff-8b7ec56f3e3f">
        <manufacturer id="73364deb-a012-4625-b759-db6a236797e3" name="Toyota"/>
        <owner id="1ddb24a4-3c7e-4ea5-a5e3-cfb8d405336e" name="J.D. Gibbs"/>
        <team id="b30dee06-c437-4e76-8b9c-8b850d52ce21" name="Joe Gibbs Racing">
        </team>
      </car>
      <driver first_name="Daniel" last_name="Suarez" full_name="Daniel Suarez" points_eligible="true" id="ebd0a08d-5308-442e-a2ae-2e40aafb3100"/>
      <pit-stops>
        <pit-stop sequence="1" lap="0" leader_lap="0" positions_gained="0" in_time="0.0" out_time="0.0"/>
        <pit-stop sequence="2" lap="71" leader_lap="72" positions_gained="0" in_time="1619.574" out_time="1669.955"/>
        <pit-stop sequence="3" lap="108" leader_lap="109" positions_gained="1" in_time="2607.182" out_time="2657.62"/>
        <pit-stop sequence="4" lap="142" leader_lap="144" positions_gained="0" in_time="4015.551" out_time="4077.305"/>
        <pit-stop sequence="5" lap="262" leader_lap="266" positions_gained="0" in_time="6876.813" out_time="6923.296"/>
        <pit-stop sequence="6" lap="284" leader_lap="289" positions_gained="0" in_time="7662.331" out_time="7906.372"/>
        <pit-stop sequence="7" lap="302" leader_lap="311" positions_gained="0" in_time="8514.809" out_time="8583.33"/>
        <pit-stop sequence="8" lap="327" leader_lap="336" positions_gained="0" in_time="9175.745" out_time="9243.736"/>
        <pit-stop sequence="9" lap="384" leader_lap="394" positions_gained="0" in_time="10580.571" out_time="10640.329"/>
        <pit-stop sequence="10" lap="489" leader_lap="500" positions_gained="0" in_time="13580.977" out_time="0.0"/>
      </pit-stops>
    </result>
    <result start_position="38" position="33" status="running" pit_stops="11" best_lap="5" best_lap_speed="90.573" best_lap_time="20.907" elapsed_time="13499.628" fastest_laps="0" avg_position="36.148" avg_speed="68.171" passes_made="12" quality_passes="0" times_passed="12" passing_differential="0" last_lap_speed="85.048" last_lap_time="22.265" avg_restart_speed="86.884" points="0" bonus_points="0" penalty_points="0" stage_1_points="0" stage_2_points="0" money="0.0" laps_led="0" times_led="0" laps_completed="486">
      <car number="51" sponsors="Spoonful of Music Foundation/Dashhub" crew_chief="Joe Lax" id="1e6c455d-a659-4523-8263-66e6544263f9">
        <manufacturer id="dbf04b7a-c4a2-4cff-9dd0-cf1977fc446e" name="Chevrolet"/>
        <owner id="41c22ea5-0caf-459c-9e97-0a13d3e6c086" name="Rick Ware"/>
        <team id="115610f5-11b9-43ff-a1b4-ef5cdab18119" name="Rick Ware Racing">
        </team>
      </car>
      <driver first_name="Timmy" last_name="Hill" full_name="Timmy Hill" id="a9988edd-7707-4a75-9ee5-d3a8cae0c8aa"/>
      <pit-stops>
        <pit-stop sequence="1" lap="0" leader_lap="0" positions_gained="0" in_time="0.0" out_time="0.0"/>
        <pit-stop sequence="2" lap="69" leader_lap="72" positions_gained="0" in_time="1614.034" out_time="1671.599"/>
        <pit-stop sequence="3" lap="105" leader_lap="109" positions_gained="0" in_time="2605.876" out_time="2658.863"/>
        <pit-stop sequence="4" lap="131" leader_lap="135" positions_gained="0" in_time="3693.344" out_time="3749.523"/>
        <pit-stop sequence="5" lap="257" leader_lap="266" positions_gained="0" in_time="6871.15" out_time="6949.96"/>
        <pit-stop sequence="6" lap="270" leader_lap="280" positions_gained="0" in_time="7380.95" out_time="7426.841"/>
        <pit-stop sequence="7" lap="302" leader_lap="311" positions_gained="0" in_time="8516.607" out_time="8573.544"/>
        <pit-stop sequence="8" lap="327" leader_lap="336" positions_gained="0" in_time="9176.569" out_time="9222.296"/>
        <pit-stop sequence="9" lap="383" leader_lap="394" positions_gained="0" in_time="10583.574" out_time="10641.879"/>
        <pit-stop sequence="10" lap="421" leader_lap="432" positions_gained="0" in_time="11993.65" out_time="12048.744"/>
        <pit-stop sequence="11" lap="486" leader_lap="500" positions_gained="0" in_time="13531.108" out_time="0.0"/>
      </pit-stops>
    </result>
    <result start_position="21" position="34" status="accident" pit_stops="9" best_lap="277" best_lap_speed="91.98" best_lap_time="20.587" elapsed_time="11431.653" fastest_laps="10" avg_position="14.571" avg_speed="69.24" passes_made="61" quality_passes="50" times_passed="45" passing_differential="16" last_lap_speed="57.885" last_lap_time="32.713" avg_restart_speed="88.898" points="8" bonus_points="5" penalty_points="0" stage_1_points="0" stage_2_points="5" money="0.0" laps_led="0" times_led="0" laps_completed="418">
      <car number="88" sponsors="Nationwide Insurance/Axalta Coatings System/Mountain Dew" crew_chief="Greg Ives" id="04b9f3bc-b614-4102-9ce9-db9fad10020d">
        <manufacturer id="dbf04b7a-c4a2-4cff-9dd0-cf1977fc446e" name="Chevrolet"/>
        <owner id="57fb4b0f-140e-47c6-8710-9e24614b4ff4" name="Rick Hendrick"/>
        <team id="8427da4c-9c88-4849-9242-0c184d5ed67c" name="Hendrick Motorsports">
          <owner id="df3acab4-1712-44bb-b913-897b4e20fd50" name="Rick Hendrick"/>
        </team>
      </car>
      <driver first_name="Dale" last_name="Earnhardt" full_name="Dale Earnhardt Jr" points_eligible="true" id="fc60204c-116b-40d8-a59e-a565e54e3fda"/>
      <pit-stops>
        <pit-stop sequence="1" lap="0" leader_lap="0" positions_gained="0" in_time="0.0" out_time="0.0"/>
        <pit-stop sequence="2" lap="71" leader_lap="71" positions_gained="-1" in_time="1572.713" out_time="1621.186"/>
        <pit-stop sequence="3" lap="108" leader_lap="108" positions_gained="4" in_time="2556.027" out_time="2597.711"/>
        <pit-stop sequence="4" lap="124" leader_lap="125" positions_gained="0" in_time="3196.803" out_time="3254.409"/>
        <pit-stop sequence="5" lap="265" leader_lap="265" positions_gained="1" in_time="6823.705" out_time="6871.085"/>
        <pit-stop sequence="6" lap="310" leader_lap="310" positions_gained="0" in_time="8453.102" out_time="8500.452"/>
        <pit-stop sequence="7" lap="335" leader_lap="335" positions_gained="0" in_time="9120.831" out_time="9167.727"/>
        <pit-stop sequence="8" lap="393" leader_lap="393" positions_gained="0" in_time="10533.384" out_time="10580.563"/>
        <pit-stop sequence="9" lap="396" leader_lap="396" positions_gained="0" in_time="10694.806" out_time="10738.732"/>
      </pit-stops>
    </result>
    <result start_position="28" position="35" status="accident" pit_stops="9" best_lap="7" best_lap_speed="91.087" best_lap_time="20.789" elapsed_time="10933.439" fastest_laps="0" avg_position="30.158" avg_speed="69.451" passes_made="23" quality_passes="0" times_passed="29" passing_differential="-6" last_lap_speed="87.565" last_lap_time="21.625" avg_restart_speed="87.563" points="2" bonus_points="0" penalty_points="0" stage_1_points="0" stage_2_points="0" money="0.0" laps_led="0" times_led="0" laps_completed="401">
      <car number="32" sponsors="Can-AM/Kappa/Keen Parts/Visone RV/E.J. Wade Foundation" crew_chief="Gene Nead" id="a5a65137-22fa-4adc-9d5b-e1f937da5992">
        <manufacturer id="12844047-ab59-43ca-ab6c-c10d54931715" name="Ford"/>
        <owner id="06ab99a6-5ed9-4baa-92dc-86ff94880b69" name="Archie St. Hilaire"/>
        <team id="81b76d72-9660-437b-85db-c3d40d7a56da" name="Go FAS Racing">
        </team>
      </car>
      <driver first_name="Matt" last_name="DiBenedetto" full_name="Matt DiBenedetto" points_eligible="true" id="06c9c0f9-392a-4f0e-aae7-39bb417af02f"/>
      <pit-stops>
        <pit-stop sequence="1" lap="0" leader_lap="0" positions_gained="0" in_time="0.0" out_time="0.0"/>
        <pit-stop sequence="2" lap="108" leader_lap="109" positions_gained="0" in_time="2602.419" out_time="2651.703"/>
        <pit-stop sequence="3" lap="134" leader_lap="135" positions_gained="0" in_time="3688.026" out_time="3736.245"/>
        <pit-stop sequence="4" lap="263" leader_lap="266" positions_gained="0" in_time="6871.689" out_time="6922.624"/>
        <pit-stop sequence="5" lap="287" leader_lap="290" positions_gained="0" in_time="7745.771" out_time="7799.541"/>
        <pit-stop sequence="6" lap="307" leader_lap="310" positions_gained="0" in_time="8466.013" out_time="8521.484"/>
        <pit-stop sequence="7" lap="309" leader_lap="312" positions_gained="0" in_time="8567.899" out_time="8620.719"/>
        <pit-stop sequence="8" lap="332" leader_lap="336" positions_gained="0" in_time="9169.356" out_time="9231.24"/>
        <pit-stop sequence="9" lap="333" leader_lap="338" positions_gained="0" in_time="9243.221" out_time="9290.995"/>
      </pit-stops>
    </result>
    <result start_position="36" position="36" status="accident" pit_stops="6" best_lap="144" best_lap_speed="89.833" best_lap_time="21.079" elapsed_time="10452.938" fastest_laps="0" avg_position="35.435" avg_speed="69.745" passes_made="7" quality_passes="0" times_passed="10" passing_differential="-3" last_lap_speed="37.159" last_lap_time="50.959" avg_restart_speed="86.518" points="1" bonus_points="0" penalty_points="0" stage_1_points="0" stage_2_points="0" money="0.0" laps_led="0" times_led="0" laps_completed="385">
      <car number="33" sponsors="Starter/Little Joes Autos /Curtis Key Plumbing" crew_chief="Pat Tryson" id="649dbd05-7d8d-4afe-b46b-1c80dafb975d">
        <manufacturer id="dbf04b7a-c4a2-4cff-9dd0-cf1977fc446e" name="Chevrolet"/>
        <owner id="f94f6ac9-3a9b-4cbf-9e07-f15b7453926c" name="Joe Falk"/>
        <team id="49d1268e-b7c9-49a7-ba3a-0ef65e3cabc6" name="Circle Sport-TMG">
          <owner id="fe666865-d1ef-49c7-987e-ac0b29ea6fd5" name="Joe Falk"/>
        </team>
      </car>
      <driver first_name="Jeffrey" last_name="Earnhardt" full_name="Jeffrey Earnhardt" points_eligible="true" id="2e33a0c7-05f0-4887-bcbd-b64606114676"/>
      <pit-stops>
        <pit-stop sequence="1" lap="0" leader_lap="0" positions_gained="0" in_time="0.0" out_time="0.0"/>
        <pit-stop sequence="2" lap="70" leader_lap="72" positions_gained="0" in_time="1618.899" out_time="1675.529"/>
        <pit-stop sequence="3" lap="132" leader_lap="135" positions_gained="0" in_time="3694.132" out_time="3743.809"/>
        <pit-stop sequence="4" lap="261" leader_lap="266" positions_gained="0" in_time="6880.73" out_time="6929.814"/>
        <pit-stop sequence="5" lap="306" leader_lap="311" positions_gained="0" in_time="8515.818" out_time="8565.265"/>
        <pit-stop sequence="6" lap="384" leader_lap="391" positions_gained="0" in_time="10432.273" out_time="10661.371"/>
      </pit-stops>
    </result>
    <result start_position="14" position="37" status="accident" pit_stops="8" best_lap="4" best_lap_speed="93.001" best_lap_time="20.361" elapsed_time="7949.775" fastest_laps="1" avg_position="25.806" avg_speed="70.268" passes_made="35" quality_passes="13" times_passed="45" passing_differential="-10" last_lap_speed="72.663" last_lap_time="26.06" avg_restart_speed="88.594" points="1" bonus_points="0" penalty_points="0" stage_1_points="0" stage_2_points="0" money="0.0" laps_led="0" times_led="0" laps_completed="295">
      <car number="41" sponsors="Monster Energy/Haas Automation/Mobil 1" crew_chief="Tony Gibson" id="ebb590f6-49ac-4bcd-a06c-9b8f7e38b5a8">
        <manufacturer id="12844047-ab59-43ca-ab6c-c10d54931715" name="Ford"/>
        <owner id="1c6be062-998b-4846-87d0-11eebfe766d8" name="Gene Haas"/>
        <team id="876a07ff-ff53-4f23-9528-6d9795270244" name="Stewart Haas Racing">
          <owner id="160c7b9e-b198-4b4d-9000-bcdc1a094cee" name="Tony Stewart"/>
        </team>
      </car>
      <driver first_name="Kurt" last_name="Busch" full_name="Kurt Busch" points_eligible="true" id="8e76a45f-596e-4b56-9eb6-0623e45bf89c"/>
      <pit-stops>
        <pit-stop sequence="1" lap="0" leader_lap="0" positions_gained="0" in_time="0.0" out_time="0.0"/>
        <pit-stop sequence="2" lap="71" leader_lap="71" positions_gained="1" in_time="1571.432" out_time="1618.05"/>
        <pit-stop sequence="3" lap="72" leader_lap="72" positions_gained="0" in_time="1618.05" out_time="0.0"/>
        <pit-stop sequence="4" lap="108" leader_lap="108" positions_gained="0" in_time="2558.292" out_time="2605.66"/>
        <pit-stop sequence="5" lap="134" leader_lap="134" positions_gained="2" in_time="3636.812" out_time="3682.54"/>
        <pit-stop sequence="6" lap="265" leader_lap="266" positions_gained="2" in_time="6878.473" out_time="6925.538"/>
        <pit-stop sequence="7" lap="288" leader_lap="290" positions_gained="0" in_time="7709.606" out_time="7761.172"/>
        <pit-stop sequence="8" lap="290" leader_lap="291" positions_gained="0" in_time="7798.566" out_time="7855.079"/>
      </pit-stops>
    </result>
    <result start_position="6" position="38" status="accident" pit_stops="2" best_lap="5" best_lap_speed="93.272" best_lap_time="20.302" elapsed_time="2858.336" fastest_laps="5" avg_position="30.337" avg_speed="82.726" passes_made="12" quality_passes="12" times_passed="18" passing_differential="-6" last_lap_speed="88.062" last_lap_time="21.503" avg_restart_speed="89.84" points="1" bonus_points="0" penalty_points="0" stage_1_points="0" stage_2_points="0" money="0.0" laps_led="0" times_led="0" laps_completed="105">
      <car number="1" sponsors="McDonald's/Cessna/GearWrench/Credit One Bank" crew_chief="Matt McCall" id="3cc7ae07-4ec7-4d14-8cdf-59557055db30">
        <manufacturer id="dbf04b7a-c4a2-4cff-9dd0-cf1977fc446e" name="Chevrolet"/>
        <owner id="f37e2acb-0f47-498f-8a3c-d2aef410cdc7" name="Felix Sabates"/>
        <team id="e9897fd1-8187-4930-814d-5d05cd43d198" name="Chip Ganassi Racing">
        </team>
      </car>
      <driver first_name="Jamie" last_name="McMurray" full_name="Jamie McMurray" points_eligible="true" id="f8d8ff36-bfcf-4d98-8eb2-353f1e8d3c34"/>
      <pit-stops>
        <pit-stop sequence="1" lap="0" leader_lap="0" positions_gained="0" in_time="0.0" out_time="0.0"/>
        <pit-stop sequence="2" lap="71" leader_lap="71" positions_gained="-2" in_time="1567.371" out_time="1615.839"/>
      </pit-stops>
    </result>
  </results>
</race>
<!-- Generation ended @ 2017-04-02 22:26:21 +0000 -->